{
    "sourceTypes" : [
        {
        "typeName": "Articles",
        "typeIdentifier": "articles"
    }, {
        "typeName": "Blogs",
        "typeIdentifier": "blogs"
    }, {
        "typeName": "Data",
        "typeIdentifier": "data"
    }, {
        "typeName": "Facts",
        "typeIdentifier": "facts"
    }, {
        "typeName": "Journals",
        "typeIdentifier": "journals"
    }, {
        "typeName": "News",
        "typeIdentifier": "news"
    }, {
        "typeName": "Photos",
        "typeIdentifier": "photos"
    }, {
        "typeName": "Social",
        "typeIdentifier": "social"
    }, {
            "typeName" : "AudioVideo",
            "typeIdentifier" : "audiovideo"
        }
    ],
    "sourceList": [{
        "feedIdentifier": "homestream",
        "typeIdentifier": "articles",
        "title": "Home",
        "icon": "ion-checkmark-circled",
        "url": "./json/sources/AggregateFeed.json",
        "processors": ["cardTemplateInjector", "stripHtml"],
        "detailType": "default",
        "showByDefault": true,
        "cardImages": true,
        "filterLocked": true,
        "templates": {
            "containerSet": "ui-container-home",
            "stream": "ui-stream-home",
            "card": "ui-card-default",
            "homeCard": "ui-card-default",
            "detail": "ui-detail-article"
        }
    }, {
        "feedIdentifier": "aroundtheworld",
        "typeIdentifier": "articles",
        "title": "CDC Around the World",
        "icon": "ion-checkmark-circled",
        "url": "./json/sources/CDCAroundtheWorld.json",
        "getContentBy": "id",
        "processors": ["cardTemplateInjector"],
        "detailType": "default",
        "showByDefault": true,
        "cardImages": true,
        "filterLocked": false,
        "templates": {
            "containerSet": "ui-container-default",
            "stream": "ui-stream-standard",
            "card": "ui-card-default",
            "homeCard": "ui-card-default",
            "detail": "ui-detail-article"
        }
    }, {
        "feedIdentifier": "diseaseoftheweek",
        "typeIdentifier": "articles",
        "title": "Disease of the Week",
        "icon": "ion-checkmark-circled",
        "url": "./json/sources/DOTW.json",
        "getContentBy": "url",
        "processors": ["cardTemplateInjector"],
        "detailType": "iframe",
        "showByDefault": true,
        "cardImages": true,
        "filterLocked": false,
        "templates": {
            "containerSet": "ui-container-iframe",
            "stream": "ui-stream-standard",
            "card": "ui-card-default",
            "homeCard": "ui-card-default",
            "detail": "ui-detail-embed"
        }
    }, {
        "feedIdentifier": "fluviewweeklyreport",
        "typeIdentifier": "articles",
        "title": "FluView Weekly Summary",
        "icon": "ion-checkmark-circled",
        "url": " ./json/sources/FluView.json",
        "getContentBy": "id",
        "processors": ["cardTemplateInjector"],
        "detailType": "default",
        "showByDefault": true,
        "cardImages": true,
        "filterLocked": false,
        "templates": {
            "containerSet": "ui-container-default",
            "stream": "ui-stream-standard",
            "card": "ui-card-default",
            "homeCard": "ui-card-default",
            "detail": "ui-detail-article"
        }
    }, {
        "feedIdentifier": "featuredhealtharticles",
        "typeIdentifier": "articles",
        "title": "Health Articles",
        "icon": "ion-checkmark-circled",
        "url": "./json/sources/HealthArticles.json",
        "getContentBy": "url",
        "processors": ["cardTemplateInjector"],
        "detailType": "iframe",
        "showByDefault": true,
        "cardImages": true,
        "filterLocked": false,
        "templates": {
            "containerSet": "ui-container-iframe",
            "stream": "ui-stream-standard",
            "card": "ui-card-default",
            "homeCard": "ui-card-default",
            "detail": "ui-detail-embed"
        }
    }, {
        "feedIdentifier": "vitalsigns",
        "typeIdentifier": "articles",
        "title": "Vital Signs",
        "icon": "ion-checkmark-circled",
        "url": "./json/sources/VitalSigns.json",
        "getContentBy": "id",
        "processors": ["cardTemplateInjector"],
        "detailType": "default",
        "showByDefault": true,
        "cardImages": false,
        "filterLocked": false,
        "templates": {
            "containerSet": "ui-container-default",
            "stream": "ui-stream-standard",
            "card": "ui-card-default",
            "homeCard": "ui-card-default",
            "detail": "ui-detail-article"
        }
    }, {
        "feedIdentifier": "faststats",
        "typeIdentifier": "data",
        "title": "FastStats",
        "icon": "ion-checkmark-circled",
        "url": "./json/sources/FastStats.json",
        "getContentBy": "id",
        "processors": ["cardTemplateInjector"],
        "detailType": "default",
        "showByDefault": true,
        "cardImages": true,
        "filterLocked": false,
        "templates": {
            "containerSet": "ui-container-default",
            "stream": "ui-stream-standard",
            "card": "ui-card-default",
            "homeCard": "ui-card-default",
            "detail": "ui-detail-data"
        }
    }, {
        "feedIdentifier": "eid",
        "typeIdentifier": "journals",
        "title": "Emerging Infectious Disease (EID)",
        "icon": "ion-checkmark-circled",
        "url": "./json/sources/EID.json",
        "getContentBy": "id",
        "processors": ["cardTemplateInjector", "stripHtml"],
        "detailType": "journal",
        "showByDefault": true,
        "cardImages": false,
        "filterLocked": false,
        "templates": {
            "containerSet": "ui-container-default",
            "stream": "ui-stream-standard",
            "card": "ui-card-default",
            "homeCard": "ui-card-default",
            "detail": "ui-detail-journal"
        }
    }, {
        "feedIdentifier": "cdcdirectorblog",
        "typeIdentifier": "blogs",
        "title": "CDC Director Blog",
        "icon": "ion-checkmark-circled",
        "url": "./json/sources/CDCDirectorsBlog.json",
        "getContentBy": "id",
        "processors": ["cardTemplateInjector"],
        "detailType": "blog",
        "showByDefault": true,
        "cardImages": true,
        "filterLocked": false,
        "templates": {
            "containerSet": "ui-container-default",
            "stream": "ui-stream-standard",
            "card": "ui-card-default",
            "homeCard": "ui-card-default",
            "detail": "ui-detail-blog"
        }
    }, {
        "feedIdentifier": "publichealthmattersblog",
        "typeIdentifier": "blogs",
        "title": "Public Health Matters Blog",
        "icon": "ion-checkmark-circled",
        "url": "./json/sources/PublicHealthMattersBlog.json",
        "getContentBy": "id",
        "processors": ["cardTemplateInjector"],
        "detailType": "blog",
        "showByDefault": true,
        "cardImages": true,
        "filterLocked": false,
        "templates": {
            "containerSet": "ui-container-default",
            "stream": "ui-stream-standard",
            "card": "ui-card-default",
            "homeCard": "ui-card-default",
            "detail": "ui-detail-blog"
        }
    }, {
        "feedIdentifier": "weeklycasecounts",
        "typeIdentifier": "data",
        "title": "Disease Case Counts",
        "icon": "ion-close-circled",
        "url": "./json/sources/",
        "getContentBy": "url",
        "processors": ["cardTemplateInjector"],
        "detailType": "default",
        "showByDefault": true,
        "cardImages": true,
        "filterLocked": false,
        "templates": {
            "containerSet": "ui-container-default",
            "stream": "ui-stream-standard",
            "card": "ui-card-default",
            "homeCard": "ui-card-default",
            "detail": "ui-detail-data"
        }
    }, {
        "feedIdentifier": "didyouknow",
        "typeIdentifier": "facts",
        "title": "Did You Know?",
        "icon": "ion-checkmark-circled",
        "url": "./json/sources/DidYouKnow.json",
        "getContentBy": "id",
        "processors": ["cardTemplateInjector", "firstOnly"],
        "detailType": "default",
        "showByDefault": true,
        "cardImages": true,
        "filterLocked": false,
        "templates": {
            "containerSet": "ui-container-default",
            "stream": "ui-stream-standard",
            "card": "ui-card-default",
            "homeCard": "ui-card-default",
            "detail": "ui-detail-fact"
        }
    }, {
        "feedIdentifier": "factsoftheweek",
        "typeIdentifier": "facts",
        "title": "Fact of the Week",
        "icon": "ion-checkmark-circled",
        "url": "./json/sources/FactoftheWeek.json",
        "getContentBy": "id",
        "processors": ["cardTemplateInjector", "parseEncoding"],
        "detailType": "default",
        "showByDefault": true,
        "cardImages": true,
        "filterLocked": false,
        "templates": {
            "containerSet": "ui-container-default",
            "stream": "ui-stream-standard",
            "card": "ui-card-default",
            "homeCard": "ui-card-default",
            "detail": "ui-detail-fact"
        }
    }, {
        "feedIdentifier": "mmwr",
        "typeIdentifier": "journals",
        "title": "Morbidity and Mortality Weekly Report (MMWR)",
        "icon": "ion-checkmark-circled",
        "url": "./json/sources/MMWR.json",
        "getContentBy": "id",
        "processors": ["cardTemplateInjector", "stripHtml"],
        "detailType": "journal",
        "showByDefault": true,
        "cardImages": true,
        "filterLocked": false,
        "templates": {
            "containerSet": "ui-container-iframe",
            "stream": "ui-stream-standard",
            "card": "ui-card-default",
            "homeCard": "ui-card-default",
            "detail": "ui-detail-journal"
        }
    }, {
        "feedIdentifier": "pcd",
        "typeIdentifier": "journals",
        "title": "Preventing Chronic Disease (PCD)",
        "icon": "ion-checkmark-circled",
        "url": "./json/sources/PCD.json",
        "getContentBy": "id",
        "processors": ["cardTemplateInjector"],
        "detailType": "journal",
        "showByDefault": true,
        "cardImages": true,
        "filterLocked": false,
        "templates": {
            "containerSet": "ui-container-default",
            "stream": "ui-stream-standard",
            "card": "ui-card-default",
            "homeCard": "ui-card-default",
            "detail": "ui-detail-journal"
        }
    }, {
        "feedIdentifier": "newsroom",
        "typeIdentifier": "news",
        "title": "Newsroom",
        "icon": "ion-checkmark-circled",
        "url": "./json/sources/NewsRoom.json",
        "getContentBy": "url",
        "detailType": "iframe",
        "showByDefault": true,
        "cardImages": true,
        "filterLocked": false,
        "templates": {
            "containerSet": "ui-container-default",
            "stream": "ui-stream-standard",
            "card": "ui-card-default",
            "homeCard": "ui-card-default",
            "detail": "ui-detail-embed"
        }
    }, {
        "feedIdentifier": "outbreaks",
        "typeIdentifier": "news",
        "title": "Outbreaks",
        "icon": "ion-checkmark-circled",
        "url": "./json/sources/Outbreaks.json",
        "getContentBy": "na",
        "processors": ["cardTemplateInjector", "flagOutbreak"],
        "detailType": "iframe",
        "showByDefault": true,
        "cardImages": false,
        "filterLocked": false,
        "templates": {
            "containerSet": "ui-container-default",
            "stream": "ui-stream-standard",
            "card": "ui-card-default",
            "homeCard": "ui-card-default",
            "detail": "ui-detail-embed"
        }
    }, {
        "feedIdentifier": "travelnotices",
        "typeIdentifier": "news",
        "title": "Travel Notices",
        "icon": "ion-checkmark-circled",
        "url": "./json/sources/TravelNotices.json",
        "getContentBy": "na",
        "processors": ["cardTemplateInjector"],
        "detailType": "iframe",
        "showByDefault": true,
        "cardImages": true,
        "filterLocked": false,
        "templates": {
            "containerSet": "ui-container-default",
            "stream": "ui-stream-standard",
            "card": "ui-card-default",
            "homeCard": "ui-card-default",
            "detail": "ui-detail-embed"
        }
    }, {
        "feedIdentifier": "imageoftheweek",
        "typeIdentifier": "photos",
        "title": "Image Library",
        "icon": "ion-checkmark-circled",
        "url": "./json/sources/PHIL.json",
        "getContentBy": "na",
        "processors": ["cardTemplateInjector"],
        "detailType": "image",
        "showByDefault": true,
        "cardImages": true,
        "filterLocked": false,
        "templates": {
            "containerSet": "ui-container-images",
            "stream": "ui-stream-image",
            "card": "ui-card-default",
            "homeCard": "ui-card-default",
            "detail": "ui-detail-image"
        }
    }, {
        "feedIdentifier": "podcasts",
        "typeIdentifier" : "audiovideo",
        "title": "Podcasts",
        "icon": "ion-checkmark-circled",
        "url": "./json/sources/Podcasts.json",
        "getContentBy": "na",
        "processors": ["cardTemplateInjector"],
        "detailType" : "default",
        "showByDefault": true,
        "cardImages": true,
        "filterLocked": false,
        "templates": {
            "containerSet": "ui-container-default",
            "stream": "ui-stream-audio",
            "card": "ui-card-default",
            "homeCard": "ui-card-default",
            "detail": "ui-detail-audio"
        }
    }, {
        "feedIdentifier": "youtube",
        "typeIdentifier" : "audiovideo",
        "title": "Videos",
        "icon": "ion-checkmark-circled",
        "url": "./json/sources/YouTube_All.json",
        "getContentBy": "na",
        "processors": ["cardTemplateInjector", "extractVideoComments"],
        "detailType": "video",
        "showByDefault": true,
        "cardImages": true,
        "filterLocked": false,
        "templates": {
            "containerSet": "ui-container-default",
            "stream": "ui-stream-standard",
            "card": "ui-card-default",
            "homeCard": "ui-card-default",
            "detail": "ui-detail-video"
        }
    }, {
        "feedIdentifier": "cdcgov",
        "typeIdentifier": "photos",
        "title": "Instagram",
        "icon": "ion-checkmark-circled",
        "getContentBy": "na",
        "detailType": "default",
        "showByDefault": true,
        "cardImages": true,
        "filterLocked": false,
        "templates": {
            "containerSet": "ui-container-default",
            "stream": "ui-stream-standard",
            "card": "ui-card-default",
            "homeCard": "ui-card-default",
            "detail": "ui-detail-article"
        }
    }, {
        "feedIdentifier": "cdcsocialmedia",
        "typeIdentifier": "photos",
        "title": "Flickr",
        "icon": "ion-checkmark-circled",
        "getContentBy": "na",
        "detailType": "photos",
        "showByDefault": true,
        "cardImages": true,
        "filterLocked": false,
        "templates": {
            "containerSet": "ui-container-default",
            "stream": "ui-stream-image",
            "card": "ui-card-default",
            "homeCard": "ui-card-default",
            "detail": "ui-detail-photos"
        }
    }, {
        "feedIdentifier": "facebook",
        "typeIdentifier": "social",
        "title": "Facebook",
        "icon": "ion-checkmark-circled",
        "getContentBy": "na",
        "detailType": "default",
        "showByDefault": true,
        "cardImages": true,
        "filterLocked": false,
        "templates": {
            "containerSet": "ui-container-default",
            "stream": "ui-stream-video",
            "card": "ui-card-default",
            "homeCard": "ui-card-default",
            "detail": "ui-detail-video"
        }
    }, {
        "feedIdentifier": "posts",
        "typeIdentifier": "social",
        "title": "Google+",
        "icon": "ion-checkmark-circled",
        "getContentBy": "na",
        "detailType": "default",
        "showByDefault": true,
        "cardImages": true,
        "filterLocked": false,
        "templates": {
            "containerSet": "ui-container-default",
            "stream": "ui-stream-standard",
            "card": "ui-card-default",
            "homeCard": "ui-card-default",
            "detail": "ui-detail-article"
        }
    }, {
        "feedIdentifier": "twitter",
        "typeIdentifier": "social",
        "title": "Twitter",
        "icon": "ion-checkmark-circled",
        "getContentBy": "na",
        "detailType": "default",
        "showByDefault": true,
        "cardImages": true,
        "filterLocked": false,
        "templates": {
            "containerSet": "ui-container-default",
            "stream": "ui-stream-standard",
            "card": "ui-card-default",
            "homeCard": "ui-card-default",
            "detail": "landing-twitter"
        }
    }, {
        "feedIdentifier": "pinterest",
        "typeIdentifier": "social",
        "title": "Pinterest",
        "icon": "ion-checkmark-circled",
        "getContentBy": "na",
        "detailType": "default",
        "showByDefault": true,
        "cardImages": true,
        "filterLocked": false,
        "templates": {
            "containerSet": "ui-container-default",
            "stream": "ui-stream-standard",
            "card": "ui-card-default",
            "homeCard": "ui-card-default",
            "detail": "ui-detail-article"
        }
    }, {
        "feedIdentifier": "civdemo",
        "typeIdentifier": "social",
        "title": "CIV Demo Page",
        "icon": "ion-checkmark-circled",
        "getContentBy": "na",
        "detailType": "default",
        "showByDefault": true,
        "cardImages": true,
        "filterLocked": false,
        "templates": {
            "containerSet": "ui-container-default",
            "stream": "ui-stream-standard",
            "card": "ui-card-default",
            "homeCard": "ui-card-default",
            "detail": "ui-detail-article"
        }
    }]
}
