{"meta":{"status":200,"message":[],"resultSet":{"id":"c8abca0c-a259-4447-a0dd-1a2c12ae805a"},"pagination":{"total":1,"count":1,"max":1,"offset":0,"pageNum":1,"totalPages":1,"sort":null,"previousUrl":"","currentUrl":"http://oadc-dmb-dev-service.cdc.gov/api/v2/resources/media/347612/syndicate.json","nextUrl":""}},"results":{"mediaId":347612,"mediaType":"Feed Item","name":"Saving lives at 18 of the world's suicide 'hot spots'","description":"<br clear='all'/><br/><br/><a href=\"http://rc.feedsportal.com/r/238386315079/u/0/f/676950/c/35492/s/4a19d3cc/sc/14/rc/1/rc.htm\" rel=\"nofollow\"><img src=\"http://rc.feedsportal.com/r/238386315079/u/0/f/676950/c/35492/s/4a19d3cc/sc/14/rc/1/rc.img\" border=\"0\"/></a><br/><br/><a href=\"http://rc.feedsportal.com/r/238386315079/u/0/f/676950/c/35492/s/4a19d3cc/sc/14/rc/2/rc.htm\" rel=\"nofollow\"><img src=\"http://rc.feedsportal.com/r/238386315079/u/0/f/676950/c/35492/s/4a19d3cc/sc/14/rc/2/rc.img\" border=\"0\"/></a><br/><br/><a href=\"http://rc.feedsportal.com/r/238386315079/u/0/f/676950/c/35492/s/4a19d3cc/sc/14/rc/3/rc.htm\" rel=\"nofollow\"><img src=\"http://rc.feedsportal.com/r/238386315079/u/0/f/676950/c/35492/s/4a19d3cc/sc/14/rc/3/rc.img\" border=\"0\"/></a><br/><br/><a href=\"http://da.feedsportal.com/r/238386315079/u/0/f/676950/c/35492/s/4a19d3cc/sc/14/a2.htm\"><img src=\"http://da.feedsportal.com/r/238386315079/u/0/f/676950/c/35492/s/4a19d3cc/sc/14/a2.img\" border=\"0\"/></a><br/><a href=\"http://adchoice.feedsportal.com/r/238386315079/u/0/f/676950/c/35492/s/4a19d3cc/sc/14/ach.htm\"><img src=\"http://adchoice.feedsportal.com/r/238386315079/u/0/f/676950/c/35492/s/4a19d3cc/sc/14/ach.img\" border=\"0\"/></a><img width=\"1\" height=\"1\" src=\"http://pi.feedsportal.com/r/238386315079/u/0/f/676950/c/35492/s/4a19d3cc/sc/14/a2t.img\" border=\"0\"/><img width=\"1\" height=\"1\" src=\"http://pi2.feedsportal.com/r/238386315079/u/0/f/676950/c/35492/s/4a19d3cc/sc/14/a2t2.img\" border=\"0\"/><img width='1' height='1' src='http://rss.cnn.com/c/35492/f/676950/s/4a19d3cc/sc/14/mf.gif' border='0'/>","sourceUrl":"http://rss.cnn.com/c/35492/f/676950/s/4a19d3cc/sc/14/l/0L0Scnn0N0C20A150C0A90C230Chealth0Csaving0Elives0Eworlds0Esuicide0Ehot0Espots0Cindex0Bhtml0Deref0Frss0Ihealth/story01.htm","targetUrl":"http://rss.cnn.com/c/35492/f/676950/s/4a19d3cc/sc/14/l/0L0Scnn0N0C20A150C0A90C230Chealth0Csaving0Elives0Eworlds0Esuicide0Ehot0Espots0Cindex0Bhtml0Deref0Frss0Ihealth/story01.htm","content":"<?xml version=\"1.0\"?>\r\n<!DOCTYPE html>\r\n<html class=\"no-js\" xmlns=\"http://www.w3.org/1999/xhtml\">\r\n<head>\r\n<meta content=\"IE=edge,chrome=1\" http-equiv=\"X-UA-Compatible\" />\r\n<meta charset=\"utf-8\" />\r\n<meta content=\"text/html\" http-equiv=\"Content-Type\" />\r\n<meta name=\"viewport\" content=\"width=device-width, initial-scale=1.0, minimum-scale=1.0\" />\r\n<link href=\"/favicon.ie9.ico\" rel=\"Shortcut Icon\" type=\"image/x-icon\" />\r\n<link href=\"http://i.cdn.turner.com/cnn/.e/img/3.0/global/misc/apple-touch-icon.png\" rel=\"apple-touch-icon\" type=\"image/png\" />\r\n<title>Saving lives at 18 of the world's suicide 'hot spots' - CNN.com</title>\r\n<meta content=\"health\" name=\"section\" />\r\n<meta content=\"2015-09-23T14:32:08Z\" property=\"og:pubdate\" />\r\n<meta content=\"2015-09-23T14:32:08Z\" name=\"pubdate\" />\r\n<meta content=\"2015-09-28T12:25:30Z\" name=\"lastmod\" />\r\n<meta content=\"http://www.cnn.com/2015/09/23/health/saving-lives-worlds-suicide-hot-spots/index.html\" property=\"og:url\" />\r\n<meta content=\"Carina Storrs, Special to CNN\" name=\"author\" />\r\n<meta content=\"Saving lives at 18 of the world's suicide 'hot spots' - CNN.com\" property=\"og:title\" />\r\n<meta content=\"Fences and other barriers can reduce suicides by up to 93%.\" property=\"og:description\" />\r\n<meta content=\"Fences and other barriers can reduce suicides by up to 93%.\" name=\"description\" />\r\n<meta content=\"health, Saving lives at 18 of the world's suicide 'hot spots' - CNN.com\" name=\"keywords\" />\r\n<meta content=\"CNN\" property=\"og:site_name\" />\r\n<meta content=\"summary_large_image\" name=\"twitter:card\" />\r\n<meta content=\"article\" property=\"og:type\" />\r\n<meta content=\"http://i2.cdn.turner.com/cnnnext/dam/assets/121019203012-golden-gate-large-169.jpg\" property=\"og:image\" />\r\n<meta content=\"http://i2.cdn.turner.com/cnnnext/dam/assets/121019203012-golden-gate-large-169.jpg\" name=\"thumbnail\" />\r\n<link rel=\"image_src\" href=\"http://i2.cdn.turner.com/cnnnext/dam/assets/121019203012-golden-gate-large-169.jpg\" />\r\n<meta property=\"vr:canonical\" content=\"http://www.cnn.com/2015/09/23/health/saving-lives-worlds-suicide-hot-spots/index.html\" />\r\n<meta content=\"80401312489\" property=\"fb:app_id\" />\r\n<link rel=\"canonical\" href=\"http://www.cnn.com/2015/09/23/health/saving-lives-worlds-suicide-hot-spots/index.html\" />\r\n<link rel=\"publisher\" href=\"https://plus.google.com/+cnn/posts\" />\r\n<link rel=\"dns-prefetch\" href=\"http://www.ugdturner.com\" />\r\n<link rel=\"dns-prefetch\" href=\"http://vrt.outbrain.com\" />\r\n<link rel=\"dns-prefetch\" href=\"http://cdn.krxd.net\" />\r\n<link rel=\"dns-prefetch\" href=\"http://consent.truste.com\" />\r\n<link rel=\"alternate\" href=\"android-app://com.cnn.mobile.android.phone/http/www.cnn.com/2015/09/23/health/saving-lives-worlds-suicide-hot-spots/index.html\" />\r\n<link type=\"text/css\" rel=\"stylesheet\" href=\"http://www.i.cdn.cnn.com/.a/1.202.0/css/global.css\" />\r\n<link type=\"text/css\" rel=\"stylesheet\" href=\"http://www.i.cdn.cnn.com/.a/1.202.0/css/pages/page-blessed2.css\" />\r\n<link type=\"text/css\" rel=\"stylesheet\" href=\"http://www.i.cdn.cnn.com/.a/1.202.0/css/pages/page-blessed1.css\" />\r\n<link type=\"text/css\" rel=\"stylesheet\" href=\"http://www.i.cdn.cnn.com/.a/1.202.0/css/pages/page.css\" />\r\n<link type=\"text/css\" rel=\"stylesheet\" media=\"non-existant-media\" href=\"http://fast.fonts.net/t/1.css?apiType=css&projectid=20d74cc5-7f7c-49a7-80ae-fa2f389c550d\" />\r\n<meta itemprop=\"articleSection\" content=\"health\" />\r\n<meta itemprop=\"dateCreated\" content=\"2015-09-23T14:32:08Z\" />\r\n<meta itemprop=\"datePublished\" content=\"2015-09-23T14:32:08Z\" />\r\n<meta itemprop=\"dateModified\" content=\"2015-09-28T12:25:30Z\" />\r\n<meta itemprop=\"url\" content=\"http://www.cnn.com/2015/09/23/health/saving-lives-worlds-suicide-hot-spots/index.html\" />\r\n<meta itemprop=\"author\" content=\"Carina Storrs, Special to CNN\" />\r\n<meta itemprop=\"headline\" content=\"Saving lives at 18 of the world's suicide 'hot spots' - CNN.com\" />\r\n<meta itemprop=\"description\" content=\"Fences and other barriers can reduce suicides by up to 93%.\" />\r\n<meta itemprop=\"keywords\" content=\"health, Saving lives at 18 of the world's suicide 'hot spots' - CNN.com\" />\r\n<meta itemprop=\"image\" content=\"http://i2.cdn.turner.com/cnnnext/dam/assets/121019203012-golden-gate-large-169.jpg\" />\r\n<meta itemprop=\"thumbnailUrl\" content=\"http://i2.cdn.turner.com/cnnnext/dam/assets/121019203012-golden-gate-large-169.jpg\" />\r\n<meta itemprop=\"alternativeHeadline\" content=\"Saving lives at 18 of the world's suicide 'hot spots'\" />\r\n</head>\r\n<body class=\"pg pg-health pg-article domestic t-light\" data-eq-pts=\"xsmall: 0, medium: 460, large: 780, full16x9: 1100\">\r\n<div class=\"user-msg\">\r\n<div class=\"user-msg--header\">\r\n<div id=\"js-user-msg--header-text\" class=\"user-msg--header-text\"></div>\r\n\r\n<div class=\"user-msg--close js-user-msg--close\"></div>\r\n</div>\r\n\r\n<div class=\"user-msg--body\">\r\n<div id=\"js-user-msg--body-text\" class=\"user-msg--body-text\"></div>\r\n</div>\r\n</div>\r\n\r\n<header id=\"nav-header\" class=\"nav-header skinny\">\r\n<div id=\"breaking-news\" class=\"breaking-news__background\">\r\n<div class=\"l-container\">\r\n<div class=\"breaking-news\">\r\n<div class=\"breaking-news__close-btn\"></div>\r\n\r\n<div class=\"breaking-news__title\"><span class=\"breaking-news__title-text\">Breaking News</span></div>\r\n\r\n<div class=\"breaking-news__msg\"></div>\r\n</div>\r\n</div>\r\n</div>\r\n\r\n<nav class=\"nav js-navigation \">\r\n<div class=\"container\"><a class=\"logo\" href=\"/\" data-analytics=\"header_logo\"></a>\r\n<div class=\"utilities drawer js-navigation-drawer\">\r\n<div id=\"weather-header\" class=\"weather\" data-analytics=\"header_weather\"></div>\r\n\r\n<div class=\"signin\"></div>\r\n\r\n<div class=\"menu-collapse js-navigation-hamburger\">\r\n<div class=\"hamburger\"></div>\r\n</div>\r\n\r\n<button class=\"search search__button search__toggle js-search-toggle\" role=\"button\"><span class=\"search__button-text\">Toggle Search</span></button>\r\n<div class=\"m-pagebadge__button\">\r\n<div class=\"m-pagebadge m-pagebadge--topright\"><a href=\"http://cnn.it/go2\" class=\"m-pagebadge__link\"><span class=\"m-pagebadge__copy\">Watch Live TV</span></a></div>\r\n</div>\r\n</div>\r\n\r\n<div class=\"edition-picker\">\r\n<div class=\"drop-down\">\r\n<div class=\"current\">U.S. Edition</div>\r\n\r\n<ul class=\"list js-edition-picker__list\" data-location=\"header\" data-analytics=\"edition-picker\">\r\n<li class=\"item item--option selected\" data-value=\"http://us.cnn.com\"><input id=\"edition-picker--edtion-header\" type=\"radio\" class=\"js-edition-preferences__choice\" name=\"edition-pref-header\" value=\"www\" /><label for=\"edition-picker--edtion-header\">U.S.</label></li>\r\n\r\n<li class=\"item item--option \" data-value=\"http://edition.cnn.com\"><input id=\"edition-picker--www-header\" type=\"radio\" class=\"js-edition-preferences__choice\" name=\"edition-pref-header\" value=\"edition\" /><label for=\"edition-picker--www-header\">International</label></li>\r\n\r\n<li class=\"item\" data-value=\"http://arabic.cnn.com\">Arabic</li>\r\n\r\n<li class=\"item\" data-value=\"http://cnnespanol.cnn.com/\">Español</li>\r\n\r\n<li class=\"item item--select\">Set edition preference</li>\r\n\r\n<li class=\"item item--confirm js-edition-preferences__confirm\">Confirm</li>\r\n</ul>\r\n</div>\r\n</div>\r\n\r\n<div class=\"search search__field\">\r\n<form method=\"get\" action=\"/search/\" name=\"headerSearch\"><input class=\"search__input-field\" type=\"text\" placeholder=\"Search CNN\" id=\"searchInputNav\" name=\"text\" /><button class=\"search__button\" type=\"submit\" role=\"button\"><span class=\"search__button-text\">Search</span></button></form>\r\n</div>\r\n\r\n<div class=\"buckets drawer\">\r\n<ul>\r\n<li class=\"bucket news selected open\"><a href=\"/\" data-analytics=\"header_news\">News</a>\r\n<div class=\"sections drawer\">\r\n<ul>\r\n<li class=\"section us \"><a href=\"/us\" data-analytics=\"header_news_us\">U.S.</a></li>\r\n\r\n<li class=\"section world \"><a href=\"/world\" data-analytics=\"header_news_world\">World</a></li>\r\n\r\n<li class=\"section politics \"><a href=\"/politics\" data-analytics=\"header_news_politics\">Politics</a></li>\r\n\r\n<li class=\"section tech \"><a href=\"/tech\" data-analytics=\"header_news_tech\">Tech</a></li>\r\n\r\n<li class=\"section health selected\"><a href=\"/health\" data-analytics=\"header_news_health\">Health</a></li>\r\n\r\n<li class=\"section entertainment \"><a href=\"/entertainment\" data-analytics=\"header_news_entertainment\">Entertainment</a></li>\r\n\r\n<li class=\"section living \"><a href=\"/living\" data-analytics=\"header_news_living\">Living</a></li>\r\n\r\n<li class=\"section travel \"><a href=\"/travel\" data-analytics=\"header_news_travel\">Travel</a></li>\r\n\r\n<li class=\"section money \"><a href=\"//money.cnn.com\" data-analytics=\"header_news_money\">Money</a></li>\r\n\r\n<li class=\"section sports \"><a href=\"//bleacherreport.com\" data-analytics=\"header_news_sports\">Sports</a></li>\r\n</ul>\r\n\r\n<div class=\"m-pagebadge m-pagebadge--topright\"><a href=\"http://cnn.it/go2\" class=\"m-pagebadge__link\"><span class=\"m-pagebadge__copy\">Watch Live TV</span></a></div>\r\n</div>\r\n</li>\r\n\r\n<li class=\"bucket video \"><a href=\"/videos\" data-analytics=\"header_video\">Video</a>\r\n<div class=\"sections drawer\">\r\n<ul>\r\n<li class=\"section cnngo \"><a href=\"//cnn.it/go\" data-analytics=\"header_video_cnngo\">CNNgo</a></li>\r\n\r\n<li class=\"section latest-news \"><a href=\"/specials/latest-news-videos\" data-analytics=\"header_video_latest-news\">Latest News</a></li>\r\n\r\n<li class=\"section must-watch-videos \"><a href=\"/specials/video-landing/gotta-watch-video-collection\" data-analytics=\"header_video_must-watch-videos\">Must Watch Videos</a></li>\r\n\r\n<li class=\"section digital-studios \"><a href=\"/specials/digital-studios\" data-analytics=\"header_video_digital-studios\">Digital Studios</a></li>\r\n</ul>\r\n\r\n<div class=\"m-pagebadge m-pagebadge--topright\"><a href=\"http://cnn.it/go2\" class=\"m-pagebadge__link\"><span class=\"m-pagebadge__copy\">Watch Live TV</span></a></div>\r\n</div>\r\n</li>\r\n\r\n<li class=\"bucket tv \"><a href=\"/tv\" data-analytics=\"header_tv\">TV</a>\r\n<div class=\"sections drawer\">\r\n<ul>\r\n<li class=\"section cnngo \"><a href=\"//cnn.it/go\" data-analytics=\"header_tv_cnngo\">CNNgo</a></li>\r\n\r\n<li class=\"section schedule \"><a href=\"/tv/schedule/cnn\" data-analytics=\"header_tv_schedule\">Schedule</a></li>\r\n\r\n<li class=\"section cnn-films \"><a href=\"/shows/cnn-films\" data-analytics=\"header_tv_cnn-films\">CNN Films</a></li>\r\n\r\n<li class=\"section shows-a-z \"><a href=\"/specials/tv/all-shows\" data-analytics=\"header_tv_shows-a-z\">Shows A-Z</a></li>\r\n\r\n<li class=\"section faces-of-cnn-worldwide \"><a href=\"/specials/tv/anchors-and-reporters\" data-analytics=\"header_tv_faces-of-cnn-worldwide\">Faces of CNN Worldwide</a></li>\r\n</ul>\r\n\r\n<div class=\"m-pagebadge m-pagebadge--topright\"><a href=\"http://cnn.it/go2\" class=\"m-pagebadge__link\"><span class=\"m-pagebadge__copy\">Watch Live TV</span></a></div>\r\n</div>\r\n</li>\r\n\r\n<li class=\"bucket opinions \"><a href=\"/opinions\" data-analytics=\"header_opinions\">Opinions</a>\r\n<div class=\"sections drawer\">\r\n<ul>\r\n<li class=\"section political-op-eds \"><a href=\"/specials/opinion/opinion-politics\" data-analytics=\"header_opinions_political-op-eds\">Political Op-Eds</a></li>\r\n\r\n<li class=\"section social-commentary \"><a href=\"/specials/opinion/opinion-social-issues\" data-analytics=\"header_opinions_social-commentary\">Social Commentary</a></li>\r\n\r\n<li class=\"section ireport \"><a href=\"//ireport.cnn.com\" data-analytics=\"header_opinions_ireport\">iReport</a></li>\r\n</ul>\r\n\r\n<div class=\"m-pagebadge m-pagebadge--topright\"><a href=\"http://cnn.it/go2\" class=\"m-pagebadge__link\"><span class=\"m-pagebadge__copy\">Watch Live TV</span></a></div>\r\n</div>\r\n</li>\r\n\r\n<li class=\"bucket more \"><a href=\"/more\" data-analytics=\"header_more\">More…</a>\r\n<div class=\"sections drawer\">\r\n<ul>\r\n<li class=\"section photos \"><a href=\"/specials/photos\" data-analytics=\"header_more_photos\">Photos</a></li>\r\n\r\n<li class=\"section longform \"><a href=\"/specials/cnn-longform\" data-analytics=\"header_more_longform\">Longform</a></li>\r\n\r\n<li class=\"section investigations \"><a href=\"/specials/cnn-investigations\" data-analytics=\"header_more_investigations\">Investigations</a></li>\r\n\r\n<li class=\"section cnn-profiles-a-z \"><a href=\"/specials/profiles/\" data-analytics=\"header_more_cnn-profiles-a-z\">CNN profiles A-Z</a></li>\r\n\r\n<li class=\"section cnn-leadership \"><a href=\"/specials/more/cnn-leadership\" data-analytics=\"header_more_cnn-leadership\">CNN Leadership</a></li>\r\n\r\n<li class=\"section Somebody's Gotta Do It \"><a href=\"/shows/mike-rowe\" data-analytics=\"header_Somebody's Gotta Do It\">Somebody's Gotta Do It</a></li>\r\n\r\n<li class=\"section Parts Unknown \"><a href=\"/shows/anthony-bourdain-parts-unknown\" data-analytics=\"header_Parts Unknown\">Parts Unknown</a></li>\r\n\r\n<li class=\"section Great American Stories \"><a href=\"/specials/us/great-american-stories\" data-analytics=\"header_Great American Stories\">Great American Stories</a></li>\r\n\r\n<li class=\"section Style \"><a href=\"/style\" data-analytics=\"header_Style\">Style</a></li>\r\n\r\n<li class=\"section Lisa Ling \"><a href=\"/shows/this-is-life-with-lisa-ling\" data-analytics=\"header_Lisa Ling\">Lisa Ling</a></li>\r\n\r\n<li class=\"section Digital Shorts \"><a href=\"/specials/videos/digital-shorts\" data-analytics=\"header_Digital Shorts\">Digital Shorts</a></li>\r\n\r\n<li class=\"section 2 Degrees \"><a href=\"/specials/opinions/two-degrees\" data-analytics=\"header_2 Degrees\">2 Degrees</a></li>\r\n\r\n<li class=\"section CNN Heroes \"><a href=\"/specials/cnn-heroes\" data-analytics=\"header_CNN Heroes\">CNN Heroes</a></li>\r\n\r\n<li class=\"section Impact Your World \"><a href=\"/specials/impact-your-world\" data-analytics=\"header_Impact Your World\">Impact Your World</a></li>\r\n</ul>\r\n\r\n<div class=\"m-pagebadge m-pagebadge--topright\"><a href=\"http://cnn.it/go2\" class=\"m-pagebadge__link\"><span class=\"m-pagebadge__copy\">Watch Live TV</span></a></div>\r\n</div>\r\n\r\n<div class=\"more-mega-nav\">\r\n<section class=\"container more-container\">\r\n<ul class=\"quick-links list\">\r\n<li class=\"title\">Quick Links</li>\r\n\r\n<li class=\"item\"><a class=\"m-navigation--quick-links\" href=\"/specials/photos\" data-analytics=\"header_photos\">Photos</a></li>\r\n\r\n<li class=\"item\"><a class=\"m-navigation--quick-links\" href=\"/specials/cnn-longform\" data-analytics=\"header_longform\">Longform</a></li>\r\n\r\n<li class=\"item\"><a class=\"m-navigation--quick-links\" href=\"/specials/cnn-investigations\" data-analytics=\"header_investigations\">Investigations</a></li>\r\n\r\n<li class=\"item\"><a class=\"m-navigation--quick-links\" href=\"/specials/profiles/\" data-analytics=\"header_cnn-profiles-a-z\">CNN profiles A-Z</a></li>\r\n\r\n<li class=\"item\"><a class=\"m-navigation--quick-links\" href=\"/specials/more/cnn-leadership\" data-analytics=\"header_cnn-leadership\">CNN Leadership</a></li>\r\n</ul>\r\n\r\n<div class=\"specials container\"><a href=\"/shows/mike-rowe\" title=\"Somebody's Gotta Do It\" class=\"m-navigation--specials-anchor\" data-analytics=\"header_Somebody's Gotta Do It\"><img alt=\"Somebody's Gotta Do It\" src=\"data:image/gif;base64,R0lGODlhEAAJAJEAAAAAAP///////wAAACH5BAEAAAIALAAAAAAQAAkAAAIKlI+py+0Po5yUFQA7\" data-img-bw=\"http://i.cdn.turner.com/cnn/.e/img/4.0/logos/mike_row_bw.jpg\" data-img=\"http://i.cdn.turner.com/cnn/.e/img/4.0/logos/mike_row.jpg\" class=\"show-poster\" /></a><a href=\"/shows/anthony-bourdain-parts-unknown\" title=\"Parts Unknown\" class=\"m-navigation--specials-anchor\" data-analytics=\"header_Parts Unknown\"><img alt=\"Parts Unknown\" src=\"data:image/gif;base64,R0lGODlhEAAJAJEAAAAAAP///////wAAACH5BAEAAAIALAAAAAAQAAkAAAIKlI+py+0Po5yUFQA7\" data-img-bw=\"http://i.cdn.turner.com/cnn/.e/img/4.0/logos/ab_season5_bw.jpg\" data-img=\"http://i.cdn.turner.com/cnn/.e/img/4.0/logos/ab_season5.jpg\" class=\"show-poster\" /></a><a href=\"/specials/us/great-american-stories\" title=\"Great American Stories\" class=\"m-navigation--specials-anchor\" data-analytics=\"header_Great American Stories\"><img alt=\"Great American Stories\" src=\"data:image/gif;base64,R0lGODlhEAAJAJEAAAAAAP///////wAAACH5BAEAAAIALAAAAAAQAAkAAAIKlI+py+0Po5yUFQA7\" data-img-bw=\"http://i.cdn.turner.com/cnn/.e/img/4.0/logos/gas_bw.jpg\" data-img=\"http://i.cdn.turner.com/cnn/.e/img/4.0/logos/gas.jpg\" class=\"show-poster\" /></a><a href=\"/style\" title=\"Style\" class=\"m-navigation--specials-anchor\" data-analytics=\"header_Style\"><img alt=\"Style\" src=\"data:image/gif;base64,R0lGODlhEAAJAJEAAAAAAP///////wAAACH5BAEAAAIALAAAAAAQAAkAAAIKlI+py+0Po5yUFQA7\" data-img-bw=\"http://i.cdn.turner.com/cnn/.e/img/4.0/logos/CNNStyle_bw.jpg\" data-img=\"http://i.cdn.turner.com/cnn/.e/img/4.0/logos/CNNStyle.jpg\" class=\"show-poster\" /></a><a href=\"/shows/this-is-life-with-lisa-ling\" title=\"Lisa Ling\" class=\"m-navigation--specials-anchor\" data-analytics=\"header_Lisa Ling\"><img alt=\"Lisa Ling\" src=\"data:image/gif;base64,R0lGODlhEAAJAJEAAAAAAP///////wAAACH5BAEAAAIALAAAAAAQAAkAAAIKlI+py+0Po5yUFQA7\" data-img-bw=\"http://i.cdn.turner.com/cnn/.e/img/4.0/logos/life_itself_bw.png\" data-img=\"http://i.cdn.turner.com/cnn/.e/img/4.0/logos/life_itself.png\" class=\"show-poster\" /></a><a href=\"/specials/videos/digital-shorts\" title=\"Digital Shorts\" class=\"m-navigation--specials-anchor\" data-analytics=\"header_Digital Shorts\"><img alt=\"Digital Shorts\" src=\"data:image/gif;base64,R0lGODlhEAAJAJEAAAAAAP///////wAAACH5BAEAAAIALAAAAAAQAAkAAAIKlI+py+0Po5yUFQA7\" data-img-bw=\"http://i.cdn.turner.com/cnn/.e/img/4.0/logos/digital_shorts/digital_shorts_bw.png\" data-img=\"http://i.cdn.turner.com/cnn/.e/img/4.0/logos/digital_shorts/digital_shorts.png\" class=\"show-poster\" /></a><a href=\"/specials/opinions/two-degrees\" title=\"2 Degrees\" class=\"m-navigation--specials-anchor\" data-analytics=\"header_2 Degrees\"><img alt=\"2 Degrees\" src=\"data:image/gif;base64,R0lGODlhEAAJAJEAAAAAAP///////wAAACH5BAEAAAIALAAAAAAQAAkAAAIKlI+py+0Po5yUFQA7\" data-img-bw=\"http://i.cdn.turner.com/cnn/.e/img/4.0/logos/two_degrees_bw.jpg\" data-img=\"http://i.cdn.turner.com/cnn/.e/img/4.0/logos/two_degrees.jpg\" class=\"show-poster\" /></a><a href=\"/specials/cnn-heroes\" title=\"CNN Heroes\" class=\"m-navigation--specials-anchor\" data-analytics=\"header_CNN Heroes\"><img alt=\"CNN Heroes\" src=\"data:image/gif;base64,R0lGODlhEAAJAJEAAAAAAP///////wAAACH5BAEAAAIALAAAAAAQAAkAAAIKlI+py+0Po5yUFQA7\" data-img-bw=\"http://i.cdn.turner.com/cnn/.e/img/4.0/logos/heroes_bw.png\" data-img=\"http://i.cdn.turner.com/cnn/.e/img/4.0/logos/heroes.png\" class=\"show-poster\" /></a><a href=\"/specials/impact-your-world\" title=\"Impact Your World\" class=\"m-navigation--specials-anchor\" data-analytics=\"header_Impact Your World\"><img alt=\"Impact Your World\" src=\"data:image/gif;base64,R0lGODlhEAAJAJEAAAAAAP///////wAAACH5BAEAAAIALAAAAAAQAAkAAAIKlI+py+0Po5yUFQA7\" data-img-bw=\"http://i.cdn.turner.com/cnn/.e/img/4.0/logos/impact_your_world_bw.png\" data-img=\"http://i.cdn.turner.com/cnn/.e/img/4.0/logos/impact_your_world.png\" class=\"show-poster\" /></a></div>\r\n</section>\r\n</div>\r\n</li>\r\n</ul>\r\n</div>\r\n\r\n<div class=\"mega-nav js-mega-nav\"></div>\r\n</div>\r\n</nav>\r\n</header>\r\n\r\n<div class=\"pg-right-rail-tall pg-wrapper \">\r\n<div class=\"pg__background__image_wrapper\"></div>\r\n\r\n<textarea class=\"ad--is-hidden\" data-ad-name=\"freewheel-rail\"></textarea>\r\n<div class=\"banner\" id=\"cnn_300x250_sync_freewheel-rail_0_banner\"><span id=\"cnn_300x250_sync_freewheel-rail_0\" class=\"_fwph\"></span>\r\n<form id=\"_fw_form_cnn_300x250_sync_freewheel-rail_0\" style=\"display:none\"><input type=\"hidden\" name=\"_fw_input_cnn_300x250_sync_freewheel-rail_0\" id=\"_fw_input_cnn_300x250_sync_freewheel-rail_0\" value=\"ptgt=s&envp=g_js&w=300&h=250&slau=300x250_sync&adUnit=300x250_sync\" /></form>\r\n\r\n<span id=\"_fw_container_cnn_300x250_sync_freewheel-rail_0\" class=\"cn-shingle__ad\"></span></div>\r\n\r\n<div class=\"ad ad--epic ad--all t-light\">\r\n<div id=\"ad_bnr_atf_01\" class=\"ad-ad_bnr_atf_01 ad-refresh-adbanner\"></div>\r\n</div>\r\n\r\n<section class=\"pg__branding \">\r\n<div class=\"l-container\">\r\n<div class=\"el-entitlement\">\r\n<div data-ad-branding=\"impact_your_world\"></div>\r\n</div>\r\n\r\n<div class=\"el-entitlement__footer\"></div>\r\n</div>\r\n</section>\r\n\r\n<article class=\"pg-rail-tall pg-rail--align-right \" itemscope=\"itemscope\" itemtype=\"http://schema.org/NewsArticle\">\r\n<div class=\"l-container\">\r\n<div class=\"m-share m-share__rail js-share-rail m-share__floating\">\r\n<div id=\"whatsappIframe\" style=\"display: none;\"></div>\r\n\r\n<div data-social-media-name=\"whatsapp\" class=\"share-bar-whatsapp-container gigya-sharebar-element gig-bar-container gig-share-bar-container\" data-url=\"whatsapp://send?text=CNN story:\" data-title=\"Saving lives at 18 of the world's suicide 'hot spots'\" data-storyurl=\"http://cnn.it/1L5VeeC\">\r\n<div class=\"gig-button-container gig-button-container-count-none gig-button-container-whatsapp gig-share-button-container gig-button-container-horizontal\">\r\n<div class=\"gig-button gig-share-button gig-button-up gig-button-count-none\"></div>\r\n</div>\r\n</div>\r\n\r\n<div class=\"js-gigya-sharebar\" data-title=\"Saving lives at 18 of the world's suicide 'hot spots'\" data-subtitle=\"\" data-description=\"Fences and other barriers can reduce suicides by up to 93%.\" data-link=\"http://cnn.it/1L5VeeC\" data-isshorturl=\"true\" data-image-src=\"http://i2.cdn.turner.com/cnnnext/dam/assets/121019203012-golden-gate-large-169.jpg\"></div>\r\n</div>\r\n\r\n<h1 class=\"pg-headline\">Saving lives at 18 of the world's suicide 'hot spots'</h1>\r\n\r\n<div class=\"metadata \">\r\n<div class=\"metadata__info js-byline-images\">\r\n<p class=\"metadata__byline\"><span class=\"metadata__byline__author\">By Carina Storrs, Special to CNN</span></p>\r\n\r\n<p class=\"update-time\">Updated 8:25 AM ET, Mon September 28, 2015 <span id=\"js-pagetop_video_source\" class=\"video__source top_source\"></span></p>\r\n</div>\r\n\r\n<div class=\"m-share m-share__rail-top js-share-rail-top m-share__floating\">\r\n<div id=\"whatsappIframe\" style=\"display: none;\"></div>\r\n\r\n<div data-social-media-name=\"whatsapp\" class=\"share-bar-whatsapp-container gigya-sharebar-element gig-bar-container gig-share-bar-container\" data-url=\"whatsapp://send?text=CNN story:\" data-title=\"Saving lives at 18 of the world's suicide 'hot spots'\" data-storyurl=\"http://cnn.it/1L5VeeC\">\r\n<div class=\"gig-button-container gig-button-container-count-none gig-button-container-whatsapp gig-share-button-container gig-button-container-horizontal\">\r\n<div class=\"gig-button gig-share-button gig-button-up gig-button-count-none\"></div>\r\n</div>\r\n</div>\r\n\r\n<div class=\"js-gigya-sharebar\" data-title=\"Saving lives at 18 of the world's suicide 'hot spots'\" data-subtitle=\"\" data-description=\"Fences and other barriers can reduce suicides by up to 93%.\" data-link=\"http://cnn.it/1L5VeeC\" data-isshorturl=\"true\" data-image-src=\"http://i2.cdn.turner.com/cnnnext/dam/assets/121019203012-golden-gate-large-169.jpg\"></div>\r\n</div>\r\n</div>\r\n\r\n<div class=\"pg-rail-tall__wrapper\">\r\n<div class=\"pg-side-of-rail pg-rail-tall__side\">\r\n<div class=\"pg-rail-tall__head js-pg-rail-tall__head\">\r\n<section class=\"zn zn-large-media zn-body zn--idx-0 zn-has-one-container\" data-eq-pts=\"xsmall: 0, medium: 460, large: 780, full16x9: 1100\" id=\"large-media\" data-vr-zone=\"zone-0-0\" data-containers=\"1\" id=\"large-media\" data-zn-id=\"large-media\">\r\n<div class=\"l-container\">\r\n<div class=\"el__video el__video--fullwidth\">\r\n<div class=\"js-media__video media__video\" id=\"media__video_large-media_0--wrapper\">\r\n<div id=\"large-media_0--thumbnail\" class=\"media__video--thumbnail\"><img class=\"media__image media__image--responsive\" alt=\"Suicide barrier for Golden Gate?\" data-src-mini=\"http://i2.cdn.turner.com/cnnnext/dam/assets/121019203012-golden-gate-small-169.jpg\" data-src-xsmall=\"http://i2.cdn.turner.com/cnnnext/dam/assets/121019203012-golden-gate-medium-plus-169.jpg\" data-src-small=\"http://i2.cdn.turner.com/cnnnext/dam/assets/121019203012-golden-gate-large-169.jpg\" data-src-medium=\"http://i2.cdn.turner.com/cnnnext/dam/assets/121019203012-golden-gate-exlarge-169.jpg\" data-src-large=\"http://i2.cdn.turner.com/cnnnext/dam/assets/121019203012-golden-gate-super-169.jpg\" data-src-full16x9=\"http://i2.cdn.turner.com/cnnnext/dam/assets/121019203012-golden-gate-full-169.jpg\" data-src-mini1x1=\"http://i2.cdn.turner.com/cnnnext/dam/assets/121019203012-golden-gate-small-11.jpg\" data-demand-load=\"not-loaded\" data-eq-pts=\"mini: 0, xsmall: 221, small: 308, medium: 461, large: 781\" src=\"data:image/gif;base64,R0lGODlhEAAJAJEAAAAAAP///////wAAACH5BAEAAAIALAAAAAAQAAkAAAIKlI+py+0Po5yUFQA7\" />\r\n<div class=\"img__preloader\"></div>\r\n\r\n<noscript><img alt=\"Suicide barrier for Golden Gate?\" class=\"media__image\" src=\"http://i2.cdn.turner.com/cnnnext/dam/assets/121019203012-golden-gate-large-169.jpg\" /></noscript></div>\r\n\r\n<div id=\"spinner_large-media_0\" class=\"video-red-spinner\"></div>\r\n\r\n<div class=\"media__video--thumbnail-wrapper\">\r\n<div class=\"video__end-slate--inactive video__end-slate js-video__end-slate\" data-eq-pts=\"xsmall: 0, small: 300, medium: 460, large: 780\">\r\n<div class=\"l-container\">\r\n<div class=\"video__end-slate__top-wrapper\">\r\n<div class=\"js-el__video__replayer-wrapper el__video__replayer-wrapper\"><img alt=\"Suicide barrier for Golden Gate?\" class=\"media__image\" itemprop=\"image\" src=\"http://i2.cdn.turner.com/cnnnext/dam/assets/121019203012-golden-gate-large-169.jpg\" /><a class=\"el__video__replay-button-wrapper\" href=\"#\" title=\"Click to watch this video\">\r\n<div class=\"js-el__video__replay-button el__video__replay-button\"></div>\r\n</a></div>\r\n\r\n<div class=\"video__end-slate__secondary\">\r\n<div style=\"margin-left: 2em\" class=\"cn cn-list-hierarchical-xs cn--idx-0\">\r\n<h3>JUST WATCHED</h3>\r\n\r\n<h2 class=\"cd__headline\"><span class=\"cd__headline-text js-cd__headline-text\">Suicide barrier for Golden Gate?</span></h2>\r\n</div>\r\n\r\n<div class=\"video__end-slate__replay\"><a class=\"js-video__end-slate__replay\">\r\n<div class=\"video__end-slate__replay-icon\"></div>\r\n</a></div>\r\n\r\n<div class=\"video__end-slate__engage__wrapper\">\r\n<div class=\"video__end-slate__engage__text\"><a class=\"js-video__end-slate__replay-text video__end-slate__replay-text\">Replay</a></div>\r\n\r\n<div class=\"video__end-slate__engage__more\"><a href=\"/videos\" class=\"video__end-slate__replay-text\">More Videos ...</a></div>\r\n</div>\r\n</div>\r\n</div>\r\n\r\n<h4>MUST WATCH</h4>\r\n\r\n<div class=\"js-video__end-slate__tertiary video__end-slate__tertiary\">\r\n<div class=\"js-video__end-slate__carousel video__end-slate__carousel\"></div>\r\n</div>\r\n</div>\r\n</div>\r\n\r\n<div id=\"large-media_0\" class=\"media__video--responsive \" data-video-id=\"health/2014/06/23/sgmd-gupta-hines-golden-gate-bridge.cnn\"></div>\r\n\r\n<div id=\"large-media_0-metadata\" class=\"metadata\"></div>\r\n</div>\r\n\r\n<div class=\"media__caption el__storyelement__title\"><span class=\"el__storyelement__header\">Suicide barrier for Golden Gate?</span> <span class=\"el__storyelement__gray\">05:56</span></div>\r\n</div>\r\n</div>\r\n</div>\r\n</section>\r\n</div>\r\n\r\n<div class=\"pg-rail-tall__body\" itemprop=\"articleBody\">\r\n<section class=\"zn zn-body-text zn-body zn--idx-0 zn-has-multiple-containers zn-has-41-containers\" data-eq-pts=\"xsmall: 0, medium: 460, large: 780, full16x9: 1100\" id=\"body-text\" data-vr-zone=\"zone-1-0\" data-containers=\"41\" id=\"body-text\" data-zn-id=\"body-text\">\r\n<div class=\"l-container\">\r\n<div class=\"el__leafmedia el__leafmedia--storyhighlights\">\r\n<div class=\"el__storyhighlights_wrapper\">\r\n<div class=\"el__storyhighlights\">\r\n<h3 class=\"el__headline\">Story highlights</h3>\r\n\r\n<ul class=\"el__storyhighlights__list\">\r\n<li class=\"el__storyhighlights__item el__storyhighlights--normal\">Hot spots are typically bridges, cliffs or other high places often used by people to commit suicide</li>\r\n\r\n<li class=\"el__storyhighlights__item el__storyhighlights--normal\">Barriers at some hot spots reduced suicides by 93%; signs with help line numbers can reduce suicide risk by 61%</li>\r\n</ul>\r\n</div>\r\n\r\n<div class=\"ad ad--epic\" data-ad-text=\"show\">\r\n<div id=\"ad_ns_btf_01\" class=\"ad-ad_ns_btf_01 ad-refresh-default\"></div>\r\n</div>\r\n</div>\r\n</div>\r\n\r\n<div class=\"el__leafmedia el__leafmedia--sourced-paragraph\">\r\n<p class=\"zn-body__paragraph\"><cite class=\"el-editorial-source\">(CNN)</cite>Since the Golden Gate Bridge was built in San Francisco in 1937, more than 1,600 people have jumped off it and died. The bridge is one of many sites around the world that are considered suicide hot spots because people use them frequently to take their own lives.</p>\r\n</div>\r\n\r\n<p class=\"zn-body__paragraph\">A new analysis suggests that several different types of interventions could help reduce the risk of suicide at these hot spots, typically bridges, cliffs or other high places.</p>\r\n\r\n<p class=\"zn-body__paragraph\">Jane Pirkis, a professor at Australia's University of Melbourne in the \r\n\r\n<a href=\"http://mspgh.unimelb.edu.au/\" target=\"_blank\">Melbourne School of Population and Global Health</a>, and colleagues in Australia and Hong Kong looked at studies on the number of suicides before and after interventions were in place in 18 different hot spots in the United States, Canada, Australia, New Zealand, China and Europe.</p>\r\n\r\n<p class=\"zn-body__paragraph\">The researchers found that installing barriers at bridges and railway platforms was associated with a reduction in suicide risk of 93%, and providing signs with help line numbers at these sites could reduce the risk by 61%.</p>\r\n\r\n<p class=\"zn-body__paragraph\">\"These numbers are phenomenal,\" said Dr. Eric D. Caine, director of the \r\n\r\n<a href=\"http://suicideprevention-icrc-s.org/\" target=\"_blank\">Injury Control Research Center for Suicide Prevention</a> at the University of Rochester Medical Center. Caine was not involved in the new study, but wrote a commentary about it. Both were \r\n\r\n<a href=\"http://www.thelancet.com/journals/lanpsy/article/PIIS2215-0366%2815%2900266-7/abstract\" target=\"_blank\">published on Wednesday in the journal Lancet</a>.</p>\r\n\r\n<p class=\"zn-body__paragraph\">However, interventions at suicide hot spots will not have a big impact on the overall suicide rate because they are only involved in a small percentage of suicides overall, Caine said. Of the approximately 40,000 people who take their own lives every year in the United States, most use guns (52%), hanging (25%) or poisoning (16%), and only a small number jump from a tall height (2%) or in front of a moving object (1%).</p>\r\n\r\n<div class=\"ad ad--epic ad--mobile\" data-ad-text=\"show\">\r\n<div id=\"ad_rect_btf_02\" class=\"ad-ad_rect_btf_02 ad-refresh-default\"></div>\r\n</div>\r\n\r\n<p class=\"zn-body__paragraph\">Although it is important to put interventions in place at common suicide locations, \"we have got to have a strategy where fewer people come to suicide attempts, (because) once someone is determined to die, it is much harder to intervene,\" Cain said. This strategy should be multifaceted and include improving mental health services and helping people who are abused, he added.</p>\r\n\r\n<p class=\"zn-body__paragraph\">The authors of the Lancet article urged interventions at suicide hot spots, \"not only to prevent so-called copycat events, but also because of the effect that suicides at these sites have on people who work at them, live near them, or frequent them for other reasons.\"</p>\r\n\r\n<p class=\"zn-body__paragraph\">The current analysis suggests that three types of strategies can have big effects: reducing access to the sites, providing information about getting help and making it easier for another person to intervene.</p>\r\n\r\n<h3>Reducing access</h3>\r\n\r\n<br />\r\n<br />\r\n<p class=\"zn-body__paragraph\">One of the most studied interventions for reducing deaths at suicide hot spots involves reducing access. It was associated with between 62% and 99% fewer suicide deaths in 10 different studies.</p>\r\n\r\n<p class=\"zn-body__paragraph\">One of the studies found that Beachy Head, one of the highest sea cliffs in the United Kingdom, had about 16 suicides a year in the 1980s and 1990s. But in the months after road access was blocked in 2001 -- because of concern over \r\n\r\n<a href=\"http://edition.cnn.com/2001/WORLD/europe/03/16/footmouth.explainer/\">an outbreak of foot-and-mouth disease</a> in animals -- the number dropped to zero. At the Jacques Cartier Bridge in Montreal, annual suicides decreased from 10 to 2.6 after the construction of a tall fence.</p>\r\n\r\n<p class=\"zn-body__paragraph\">It is not surprising that these physical barriers help reduce suicide deaths, said Steven Vannoy, associate professor of counseling and school psychology at University of Massachusetts Boston. \"If people encounter something that slows them down, that makes them have to be conscious of what they're doing, that may psychologically cause them to not do it,\" he said. People want to think the suicide will be easy and effective, he added.</p>\r\n\r\n<p class=\"zn-body__paragraph\">Other suicide hot spots where barriers were linked with fewer suicides were:</p>\r\n\r\n<p class=\"zn-body__paragraph\">• Ellington Bridge in Washington</p>\r\n\r\n<p class=\"zn-body__paragraph\">• Memorial Bridge in Augusta, Maine</p>\r\n\r\n<p class=\"zn-body__paragraph\">• Bloor Street Viaduct in Toronto</p>\r\n\r\n<p class=\"zn-body__paragraph\">• Clifton Suspension Bridge in Bristol, England</p>\r\n\r\n<p class=\"zn-body__paragraph\">• Canton Hospital in Baden, Switzerland</p>\r\n\r\n<p class=\"zn-body__paragraph\">• Muenster Terrace in Bern, Switzerland</p>\r\n\r\n<p class=\"zn-body__paragraph\">• Gateway Bridge in Brisbane, Australia</p>\r\n\r\n<p class=\"zn-body__paragraph\">• Gap Park in Sydney</p>\r\n\r\n<p class=\"zn-body__paragraph\">• Grafton Bridge in Auckland, New Zealand</p>\r\n\r\n<p class=\"zn-body__paragraph\">• Lawyers Head cliff in Dunedin, New Zealand</p>\r\n\r\n<p class=\"zn-body__paragraph\">• The underground railway system in Hong Kong</p>\r\n\r\n<div class=\"el__embedded el__embedded--standard\">\r\n<div class=\"el__video--standard js__video--standard\" data-autoplay=\"false\">\r\n<div class=\"el__video__close--standard js__video__close--standard el__storyelements--close\"></div>\r\n\r\n<div class=\"js-media__video media__video\" id=\"media__video_body-text_28--wrapper\">\r\n<div id=\"body-text_28--thumbnail\" class=\"media__video--thumbnail\"><img class=\"media__image media__image--responsive\" alt=\"Families praise suicide barrier approval\" data-src-mini=\"http://i2.cdn.turner.com/cnnnext/dam/assets/140627192807-bts-golden-gate-bridge-suicide-barrier-reax-00000209-hp-video.jpg\" data-src-xsmall=\"http://i2.cdn.turner.com/cnnnext/dam/assets/140627192807-bts-golden-gate-bridge-suicide-barrier-reax-00000209-story-body.jpg\" data-src-small=\"http://i2.cdn.turner.com/cnnnext/dam/assets/140627192807-bts-golden-gate-bridge-suicide-barrier-reax-00000209-story-top.jpg\" data-src-medium=\"http://i2.cdn.turner.com/cnnnext/dam/assets/140627192807-bts-golden-gate-bridge-suicide-barrier-reax-00000209-horizontal-large-gallery.jpg\" data-src-large=\"http://i2.cdn.turner.com/cnnnext/dam/assets/140627192807-bts-golden-gate-bridge-suicide-barrier-reax-00000209-horizontal-large-gallery.jpg\" data-src-full16x9=\"http://i2.cdn.turner.com/cnnnext/dam/assets/140627192807-bts-golden-gate-bridge-suicide-barrier-reax-00000209-horizontal-large-gallery.jpg\" data-src-mini1x1=\"http://i2.cdn.turner.com/cnnnext/dam/assets/140627192807-bts-golden-gate-bridge-suicide-barrier-reax-00000209-topics.jpg\" data-demand-load=\"not-loaded\" data-eq-pts=\"mini: 0, xsmall: 221, small: 308, medium: 461, large: 781\" src=\"data:image/gif;base64,R0lGODlhEAAJAJEAAAAAAP///////wAAACH5BAEAAAIALAAAAAAQAAkAAAIKlI+py+0Po5yUFQA7\" />\r\n<div class=\"img__preloader\"></div>\r\n\r\n<noscript><img alt=\"Families praise suicide barrier approval\" class=\"media__image\" src=\"http://i2.cdn.turner.com/cnnnext/dam/assets/140627192807-bts-golden-gate-bridge-suicide-barrier-reax-00000209-story-top.jpg\" /></noscript>\r\n<div aria-hidden=\"true\" class=\"js-video-demand media__video--demand\"></div>\r\n\r\n<div aria-hidden=\"true\" class=\"js-video-demand media__video--demand\"></div>\r\n</div>\r\n\r\n<div id=\"spinner_body-text_28\" class=\"video-red-spinner\"></div>\r\n\r\n<div class=\"media__video--thumbnail-wrapper\">\r\n<div class=\"video__end-slate--inactive video__end-slate js-video__end-slate\" data-eq-pts=\"xsmall: 0, small: 300, medium: 460, large: 780\">\r\n<div class=\"l-container\">\r\n<div class=\"video__end-slate__top-wrapper\">\r\n<div class=\"js-el__video__replayer-wrapper el__video__replayer-wrapper\"><img alt=\"Families praise suicide barrier approval\" class=\"media__image\" itemprop=\"image\" src=\"http://i2.cdn.turner.com/cnnnext/dam/assets/140627192807-bts-golden-gate-bridge-suicide-barrier-reax-00000209-story-top.jpg\" /><a class=\"el__video__replay-button-wrapper\" href=\"#\" title=\"Click to watch this video\">\r\n<div class=\"js-el__video__replay-button el__video__replay-button\"></div>\r\n</a></div>\r\n\r\n<div class=\"video__end-slate__secondary\">\r\n<div style=\"margin-left: 2em\" class=\"cn cn-list-hierarchical-xs cn--idx-0\">\r\n<h3>JUST WATCHED</h3>\r\n\r\n<h2 class=\"cd__headline\"><span class=\"cd__headline-text js-cd__headline-text\">Families praise suicide barrier approval</span></h2>\r\n</div>\r\n\r\n<div class=\"video__end-slate__replay\"><a class=\"js-video__end-slate__replay\">\r\n<div class=\"video__end-slate__replay-icon\"></div>\r\n</a></div>\r\n\r\n<div class=\"video__end-slate__engage__wrapper\">\r\n<div class=\"video__end-slate__engage__text\"><a class=\"js-video__end-slate__replay-text video__end-slate__replay-text\">Replay</a></div>\r\n\r\n<div class=\"video__end-slate__engage__more\"><a href=\"/videos\" class=\"video__end-slate__replay-text\">More Videos ...</a></div>\r\n</div>\r\n</div>\r\n</div>\r\n\r\n<h4>MUST WATCH</h4>\r\n\r\n<div class=\"js-video__end-slate__tertiary video__end-slate__tertiary\">\r\n<div class=\"js-video__end-slate__carousel video__end-slate__carousel\"></div>\r\n</div>\r\n</div>\r\n</div>\r\n\r\n<div id=\"body-text_28\" class=\"media__video--responsive \" data-video-id=\"us/2014/06/27/bts-golden-gate-bridge-suicide-barrier-reax.cnn\"></div>\r\n\r\n<div id=\"body-text_28-metadata\" class=\"metadata\"></div>\r\n</div>\r\n\r\n<div class=\"media__caption el__storyelement__title\"><span class=\"el__storyelement__header\">Families praise suicide barrier approval</span> <span class=\"el__storyelement__gray\">01:02</span></div>\r\n</div>\r\n</div>\r\n</div>\r\n\r\n<p class=\"zn-body__paragraph\">The Golden Gate Bridge does not currently have any barriers in place, although a plan has been approved to build a steel net 20 feet below where people jump. \"There is a good reason to believe it would reduce the number of suicides,\" Vannoy said.</p>\r\n\r\n<h3>Offering help</h3>\r\n\r\n<br />\r\n<br />\r\n<p class=\"zn-body__paragraph\">Several studies have looked at the impact of encouraging people to get help, such as installing signs with numbers for suicide hotlines and crisis telephones in the hotspot area.</p>\r\n\r\n<p class=\"zn-body__paragraph\">At the Mid-Hudson Bridge in upstate New York, there were five suicides per year on average in the years before signs and crisis phones were installed, compared with 2.3 suicides after.</p>\r\n\r\n<p class=\"zn-body__paragraph\">Signs providing numbers for help had similar effects at a car park in southern England where people would go to poison themselves on car exhaust.</p>\r\n\r\n<p class=\"zn-body__paragraph\">However, crisis telephones had the opposite effect on the Skyway Bridge in St. Petersburg, Florida, where 3.7 people per year took their own lives before phones were installed in 1999, compared with 8.2 people after. The authors of the analysis suggest this increase could have been due to a website that promoted suicides using the bridge, which became popular around the same time the phones were added.</p>\r\n\r\n<h3>Patrolling the area</h3>\r\n\r\n<br />\r\n<br />\r\n<p class=\"zn-body__paragraph\">Some sites have stationed police officers on bridges and cliffs to help intervene in suicide attempts. But studies have only looked at the effects of these efforts in combination with installing fences or crisis phones and not on their own.</p>\r\n\r\n<p class=\"zn-body__paragraph\">In a study in Cheung Chau, an island off Hong Kong, programs that included police patrols as well as phone hotlines were found to reduce the number of suicides from about 8.7 to 1.7 per year. The area is considered a suicide hot spot because people rent holiday apartments where they poison themselves with carbon monoxide.</p>\r\n\r\n<p class=\"zn-body__paragraph\">Having a person intervene could probably be very effective, but somebody would have to be present at all times, Vannoy said. \"Just having a witness there can slow somebody down and make them think about what they're doing,\" he said, adding that most people who want to attempt suicide do not want others to see them.</p>\r\n\r\n<p class=\"zn-body__paragraph\">Having someone patrol a suicide hot spot could be a much less expensive strategy, and possibly more cost-effective, than projects like the steel net below the Golden Gate Bridge, Vannoy said.</p>\r\n</div>\r\n</section>\r\n\r\n<div class=\"pg-body__social\"></div>\r\n\r\n<section class=\"zn zn-story-bottom zn-single-column zn--idx-1 zn-has-two-containers\" data-eq-pts=\"xsmall: 0, medium: 460, large: 780, full16x9: 1100\" id=\"story-bottom\" data-vr-zone=\"zone-1-1\">\r\n<div class=\"ad ad--epic ad--mobile\" data-ad-text=\"show\">\r\n<div data-ad-id=\"freewheel-rail-placeholder\" data-ad-position=\"mobile\" data-ad-refresh=\"default\"></div>\r\n</div>\r\n\r\n<div class=\"ad ad--epic ad--mobile\" data-ad-text=\"show\">\r\n<div data-ad-id=\"ad_rect_atf_01\" data-ad-position=\"mobile\" data-ad-refresh=\"adtop\">\r\n<div id=\"ad_rect_atf_01\" class=\"ad-ad_rect_atf_01 ad-refresh-adtop\"></div>\r\n</div>\r\n</div>\r\n\r\n<div class=\"zn-top\">\r\n<div class=\"zn-top__background\"></div>\r\n</div>\r\n\r\n<div class=\"l-container zn__background--content-relative\">\r\n<div class=\"zn__containers\">\r\n<div class=\"column\">\r\n<ul class=\"cn cn-list-hierarchical-small-horizontal cn--idx-0 cn-\">\r\n<li>\r\n<article class=\"cd cd--tool cd--tool__outbrain\" data-analytics=\"tool-type_list-hierarchical-small-horizontal_outbrain\" data-vr-contentbox=\"\" data-eq-pts=\"xsmall: 0, small: 300, medium: 460, large: 780\">\r\n<div class=\"OB_AR_36\">\r\n<div class=\"OUTBRAIN js-m-outbrain m-outbrain\" data-src=\"http://www.cnn.com/2015/09/23/health/saving-lives-worlds-suicide-hot-spots/index.html\" data-widget-id=\"AR_36\" data-ob-template=\"cnn\"></div>\r\n</div>\r\n</article>\r\n</li>\r\n</ul>\r\n</div>\r\n\r\n<div class=\"column\">\r\n<ul class=\"cn cn-list-hierarchical-small-horizontal cn--idx-1 cn-\">\r\n<li>\r\n<article class=\"cd cd--tool cd--tool__outbrain\" data-analytics=\"tool-type_list-hierarchical-small-horizontal_outbrain\" data-vr-contentbox=\"\" data-eq-pts=\"xsmall: 0, small: 300, medium: 460, large: 780\">\r\n<div class=\"OB_AR_13\">\r\n<div class=\"OUTBRAIN js-m-outbrain m-outbrain\" data-src=\"http://www.cnn.com/2015/09/23/health/saving-lives-worlds-suicide-hot-spots/index.html\" data-widget-id=\"AR_13\" data-ob-template=\"cnn\"></div>\r\n</div>\r\n</article>\r\n</li>\r\n</ul>\r\n</div>\r\n</div>\r\n</div>\r\n</section>\r\n\r\n<section class=\"zn zn-ad-spon-1pagnmr zn-left-fluid zn--idx-2 zn-left-fluid-share zn-has-one-container\" data-eq-pts=\"xsmall: 0, medium: 460, large: 780, full16x9: 1100\" id=\"ad-spon-1pagnmr\" data-vr-zone=\"zone-1-2\" data-containers=\"1\">\r\n<div class=\"zn-top \">\r\n<div class=\"l-container zn-top__label\"></div>\r\n\r\n<div class=\"l-container zn-top__banner\"></div>\r\n\r\n<div class=\"zn-top__background\"></div>\r\n</div>\r\n\r\n<div class=\"l-container\">\r\n<div class=\"zn__containers\">\r\n<div class=\"column zn__column--idx-0\">\r\n<div class=\"ad ad--epic ad--desktop\" data-ad-text=\"show\">\r\n<div id=\"ad_bnr_btf_02\" class=\"ad-ad_bnr_btf_02 ad-refresh-adbody\"></div>\r\n</div>\r\n</div>\r\n</div>\r\n</div>\r\n</section>\r\n</div>\r\n</div>\r\n\r\n<div class=\"pg-rail pg-rail-tall__rail\">\r\n<section class=\"zn zn-Rail zn-balanced zn--idx-0 zn-has-multiple-containers zn-has-5-containers\" data-eq-pts=\"xsmall: 0, medium: 460, large: 780, full16x9: 1100\" id=\"Rail\" data-vr-zone=\"zone-2-0\" data-zone-label=\"Rail Zone\" data-containers=\"5\" data-zn-id=\"Rail\">\r\n<div class=\"ad ad--epic ad--mobile\" data-ad-text=\"show\">\r\n<div data-ad-id=\"ad_rect_btf_01\" data-ad-position=\"mobile\" data-ad-refresh=\"adbody\">\r\n<div id=\"ad_rect_btf_01\" class=\"ad-ad_rect_btf_01 ad-refresh-adbody\"></div>\r\n</div>\r\n</div>\r\n\r\n<div class=\"zn-top\">\r\n<div class=\"zn-top__background\"></div>\r\n</div>\r\n\r\n<div class=\"l-container zn__background--content-relative\">\r\n<div class=\"zn__containers\">\r\n<div class=\"column\">\r\n<div class=\"ad ad--epic ad--desktop\" data-ad-text=\"show\">\r\n<div data-ad-id=\"freewheel-rail-placeholder\" data-ad-position=\"desktop\" data-ad-refresh=\"default\"></div>\r\n</div>\r\n\r\n<div class=\"ad ad--epic ad--desktop\" data-ad-text=\"show\">\r\n<div data-ad-id=\"ad_rect_atf_01\" data-ad-position=\"desktop\" data-ad-refresh=\"adtop\"></div>\r\n</div>\r\n\r\n<ul class=\"cn cn-list-small-horizontal cn--idx-0 cn-coverageContainer_A74F6029-9333-D362-22DF-C61ABAB01DB0 cn--expandable\">\r\n<li style=\"list-style: none\">\r\n<h2 class=\"cn__title \" data-analytics=\"The%20latest%20from%20CNN%20Health_list-small-horizontal_\">The latest from CNN Health</h2>\r\n</li>\r\n\r\n<li>\r\n<article class=\"cd cd--card cd--article cd--idx-0 cd--small cd--horizontal cd--has-siblings cd--has-media cd--media__image\" data-vr-contentbox=\"/2015/09/21/health/gun-laws-youth-carrying/index.html\" data-eq-pts=\"xsmall: 0, small: 300, medium: 460, large: 780, full16x9: 1100\">\r\n<div class=\"cd__wrapper\" data-analytics=\"The%20latest%20from%20CNN%20Health_list-small-horizontal_article_\">\r\n<div class=\"media\"><a href=\"/2015/09/21/health/gun-laws-youth-carrying/index.html\"><img class=\"media__image media__image--responsive\" alt=\"NEW YORK, NY - AUGUST 19: Guns seized by the New York Police Department (NYPD), in the largest seizure of illegal guns in the city&#39;s history, are displayed on a table during a press conference on August 19, 2013 in New York City. The operation, which involved an undercover agent buying guns that were smuggled from North Carolina and South Carolina, yielded over 250 guns. ninteen people have been charged in the operation. (Photo by Andrew Burton/Getty Images)\" data-src-mini=\"http://i2.cdn.turner.com/cnnnext/dam/assets/140730113813-01-guns-file-small-169.jpg\" data-src-xsmall=\"http://i2.cdn.turner.com/cnnnext/dam/assets/140730113813-01-guns-file-medium-plus-169.jpg\" data-src-small=\"http://i2.cdn.turner.com/cnnnext/dam/assets/140730113813-01-guns-file-large-169.jpg\" data-src-medium=\"http://i2.cdn.turner.com/cnnnext/dam/assets/140730113813-01-guns-file-exlarge-169.jpg\" data-src-large=\"http://i2.cdn.turner.com/cnnnext/dam/assets/140730113813-01-guns-file-super-169.jpg\" data-src-full16x9=\"http://i2.cdn.turner.com/cnnnext/dam/assets/140730113813-01-guns-file-full-169.jpg\" data-src-mini1x1=\"http://i2.cdn.turner.com/cnnnext/dam/assets/140730113813-01-guns-file-small-11.jpg\" data-demand-load=\"not-loaded\" data-eq-pts=\"mini: 0, xsmall: 221, small: 308, medium: 461, large: 781\" src=\"data:image/gif;base64,R0lGODlhEAAJAJEAAAAAAP///////wAAACH5BAEAAAIALAAAAAAQAAkAAAIKlI+py+0Po5yUFQA7\" />\r\n<div class=\"img__preloader\"></div>\r\n\r\n<noscript><img alt=\"NEW YORK, NY - AUGUST 19: Guns seized by the New York Police Department (NYPD), in the largest seizure of illegal guns in the city&#39;s history, are displayed on a table during a press conference on August 19, 2013 in New York City. The operation, which involved an undercover agent buying guns that were smuggled from North Carolina and South Carolina, yielded over 250 guns. ninteen people have been charged in the operation. (Photo by Andrew Burton/Getty Images)\" class=\"media__image\" src=\"http://i2.cdn.turner.com/cnnnext/dam/assets/140730113813-01-guns-file-large-169.jpg\" /></noscript></a></div>\r\n\r\n<div class=\"cd__content\">\r\n<h3 class=\"cd__headline\" data-analytics=\"The%20latest%20from%20CNN%20Health_list-small-horizontal_article_\"><a href=\"/2015/09/21/health/gun-laws-youth-carrying/index.html\"><span class=\"cd__headline-text\">Stricter state gun laws keep firearms out of teens' hands</span></a></h3>\r\n</div>\r\n</div>\r\n</article>\r\n</li>\r\n\r\n<li>\r\n<article class=\"cd cd--card cd--article cd--idx-1 cd--small cd--horizontal cd--has-siblings cd--has-media cd--media__image\" data-vr-contentbox=\"/2015/09/18/health/nfl-brain-study-cte/index.html\" data-eq-pts=\"xsmall: 0, small: 300, medium: 460, large: 780, full16x9: 1100\">\r\n<div class=\"cd__wrapper\" data-analytics=\"The%20latest%20from%20CNN%20Health_list-small-horizontal_article_\">\r\n<div class=\"media\"><a href=\"/2015/09/18/health/nfl-brain-study-cte/index.html\"><img class=\"media__image media__image--responsive\" alt=\"\" data-src-mini=\"http://i2.cdn.turner.com/cnnnext/dam/assets/141230144746-danny-cevallos-concussions-football-helmets-image-1-orig-ms-hp-video.jpg\" data-src-xsmall=\"http://i2.cdn.turner.com/cnnnext/dam/assets/141230144746-danny-cevallos-concussions-football-helmets-image-1-orig-ms-story-body.jpg\" data-src-small=\"http://i2.cdn.turner.com/cnnnext/dam/assets/141230144746-danny-cevallos-concussions-football-helmets-image-1-orig-ms-story-top.jpg\" data-src-medium=\"http://i2.cdn.turner.com/cnnnext/dam/assets/141230144746-danny-cevallos-concussions-football-helmets-image-1-orig-ms-horizontal-large-gallery.jpg\" data-src-large=\"http://i2.cdn.turner.com/cnnnext/dam/assets/141230144746-danny-cevallos-concussions-football-helmets-image-1-orig-ms-horizontal-large-gallery.jpg\" data-src-full16x9=\"http://i2.cdn.turner.com/cnnnext/dam/assets/141230144746-danny-cevallos-concussions-football-helmets-image-1-orig-ms-horizontal-large-gallery.jpg\" data-src-mini1x1=\"http://i2.cdn.turner.com/cnnnext/dam/assets/141230144746-danny-cevallos-concussions-football-helmets-image-1-orig-ms-topics.jpg\" data-demand-load=\"not-loaded\" data-eq-pts=\"mini: 0, xsmall: 221, small: 308, medium: 461, large: 781\" src=\"data:image/gif;base64,R0lGODlhEAAJAJEAAAAAAP///////wAAACH5BAEAAAIALAAAAAAQAAkAAAIKlI+py+0Po5yUFQA7\" />\r\n<div class=\"img__preloader\"></div>\r\n\r\n<noscript><img alt=\"\" class=\"media__image\" src=\"http://i2.cdn.turner.com/cnnnext/dam/assets/141230144746-danny-cevallos-concussions-football-helmets-image-1-orig-ms-story-top.jpg\" /></noscript></a></div>\r\n\r\n<div class=\"cd__content\">\r\n<h3 class=\"cd__headline\" data-analytics=\"The%20latest%20from%20CNN%20Health_list-small-horizontal_article_\"><a href=\"/2015/09/18/health/nfl-brain-study-cte/index.html\"><span class=\"cd__headline-text\">87 of 91 tested ex-NFL players had brain disease linked to head trauma</span></a></h3>\r\n</div>\r\n</div>\r\n</article>\r\n</li>\r\n\r\n<li>\r\n<article class=\"cd cd--card cd--article cd--idx-2 cd--small cd--horizontal cd--has-siblings cd--has-media cd--media__image\" data-vr-contentbox=\"/2015/09/16/health/air-pollution-deaths-rising/index.html\" data-eq-pts=\"xsmall: 0, small: 300, medium: 460, large: 780, full16x9: 1100\">\r\n<div class=\"cd__wrapper\" data-analytics=\"The%20latest%20from%20CNN%20Health_list-small-horizontal_article_\">\r\n<div class=\"media\"><a href=\"/2015/09/16/health/air-pollution-deaths-rising/index.html\"><img class=\"media__image media__image--responsive\" alt=\"Hyderabad, INDIA: An Indian mother and her son burn waste in order to retrieve the copper wire at the garbage dump in the Borabanda slum in Hyderabad, 05 June 2007, on the occasion of World Environment Day. World Environment Day, commemorated each year 05 June, is one of the principal vehicles through which the United Nations stimulates worldwide awareness of the environment and enhances political attention and action. AFP PHOTO / NOAH SEELAM (Photo credit should read NOAH SEELAM/AFP/Getty Images)\" data-src-mini=\"http://i2.cdn.turner.com/cnnnext/dam/assets/150916092735-01-air-pollution-inida-2007-small-169.jpg\" data-src-xsmall=\"http://i2.cdn.turner.com/cnnnext/dam/assets/150916092735-01-air-pollution-inida-2007-medium-plus-169.jpg\" data-src-small=\"http://i2.cdn.turner.com/cnnnext/dam/assets/150916092735-01-air-pollution-inida-2007-large-169.jpg\" data-src-medium=\"http://i2.cdn.turner.com/cnnnext/dam/assets/150916092735-01-air-pollution-inida-2007-exlarge-169.jpg\" data-src-large=\"http://i2.cdn.turner.com/cnnnext/dam/assets/150916092735-01-air-pollution-inida-2007-super-169.jpg\" data-src-full16x9=\"http://i2.cdn.turner.com/cnnnext/dam/assets/150916092735-01-air-pollution-inida-2007-full-169.jpg\" data-src-mini1x1=\"http://i2.cdn.turner.com/cnnnext/dam/assets/150916092735-01-air-pollution-inida-2007-small-11.jpg\" data-demand-load=\"not-loaded\" data-eq-pts=\"mini: 0, xsmall: 221, small: 308, medium: 461, large: 781\" src=\"data:image/gif;base64,R0lGODlhEAAJAJEAAAAAAP///////wAAACH5BAEAAAIALAAAAAAQAAkAAAIKlI+py+0Po5yUFQA7\" />\r\n<div class=\"img__preloader\"></div>\r\n\r\n<noscript><img alt=\"Hyderabad, INDIA: An Indian mother and her son burn waste in order to retrieve the copper wire at the garbage dump in the Borabanda slum in Hyderabad, 05 June 2007, on the occasion of World Environment Day. World Environment Day, commemorated each year 05 June, is one of the principal vehicles through which the United Nations stimulates worldwide awareness of the environment and enhances political attention and action. AFP PHOTO / NOAH SEELAM (Photo credit should read NOAH SEELAM/AFP/Getty Images)\" class=\"media__image\" src=\"http://i2.cdn.turner.com/cnnnext/dam/assets/150916092735-01-air-pollution-inida-2007-large-169.jpg\" /></noscript></a></div>\r\n\r\n<div class=\"cd__content\">\r\n<h3 class=\"cd__headline\" data-analytics=\"The%20latest%20from%20CNN%20Health_list-small-horizontal_article_\"><a href=\"/2015/09/16/health/air-pollution-deaths-rising/index.html\"><span class=\"cd__headline-text\">More than 6 million could die early from air pollution every year</span></a></h3>\r\n</div>\r\n</div>\r\n</article>\r\n</li>\r\n\r\n<li>\r\n<article class=\"cd cd--card cd--article cd--idx-3 cd--small cd--horizontal cd--has-siblings cd--has-media cd--media__image\" data-vr-contentbox=\"/2015/09/15/health/fast-food-meat-antibiotics-grades/index.html\" data-eq-pts=\"xsmall: 0, small: 300, medium: 460, large: 780, full16x9: 1100\">\r\n<div class=\"cd__wrapper\" data-analytics=\"The%20latest%20from%20CNN%20Health_list-small-horizontal_article_\">\r\n<div class=\"media\"><a href=\"/2015/09/15/health/fast-food-meat-antibiotics-grades/index.html\"><img class=\"media__image media__image--responsive\" alt=\"Chipotle \" data-src-mini=\"http://i2.cdn.turner.com/cnnnext/dam/assets/150914175529-11-chipotle-small-169.jpg\" data-src-xsmall=\"http://i2.cdn.turner.com/cnnnext/dam/assets/150914175529-11-chipotle-medium-plus-169.jpg\" data-src-small=\"http://i2.cdn.turner.com/cnnnext/dam/assets/150914175529-11-chipotle-large-169.jpg\" data-src-medium=\"http://i2.cdn.turner.com/cnnnext/dam/assets/150914175529-11-chipotle-exlarge-169.jpg\" data-src-large=\"http://i2.cdn.turner.com/cnnnext/dam/assets/150914175529-11-chipotle-super-169.jpg\" data-src-full16x9=\"http://i2.cdn.turner.com/cnnnext/dam/assets/150914175529-11-chipotle-full-169.jpg\" data-src-mini1x1=\"http://i2.cdn.turner.com/cnnnext/dam/assets/150914175529-11-chipotle-small-11.jpg\" data-demand-load=\"not-loaded\" data-eq-pts=\"mini: 0, xsmall: 221, small: 308, medium: 461, large: 781\" src=\"data:image/gif;base64,R0lGODlhEAAJAJEAAAAAAP///////wAAACH5BAEAAAIALAAAAAAQAAkAAAIKlI+py+0Po5yUFQA7\" />\r\n<div class=\"img__preloader\"></div>\r\n\r\n<noscript><img alt=\"Chipotle \" class=\"media__image\" src=\"http://i2.cdn.turner.com/cnnnext/dam/assets/150914175529-11-chipotle-large-169.jpg\" /></noscript></a></div>\r\n\r\n<div class=\"cd__content\">\r\n<h3 class=\"cd__headline\" data-analytics=\"The%20latest%20from%20CNN%20Health_list-small-horizontal_article_\"><a href=\"/2015/09/15/health/fast-food-meat-antibiotics-grades/index.html\"><span class=\"cd__headline-text\">What's in the meat that you eat?</span></a></h3>\r\n</div>\r\n</div>\r\n</article>\r\n</li>\r\n\r\n<li>\r\n<article class=\"cd cd--card cd--article cd--idx-4 cd--small cd--horizontal cd--has-siblings cd--has-media cd--media__image\" data-vr-contentbox=\"/2015/09/18/health/high-school-football-injuries/index.html\" data-eq-pts=\"xsmall: 0, small: 300, medium: 460, large: 780, full16x9: 1100\">\r\n<div class=\"cd__wrapper\" data-analytics=\"The%20latest%20from%20CNN%20Health_list-small-horizontal_article_\">\r\n<div class=\"media\"><a href=\"/2015/09/18/health/high-school-football-injuries/index.html\"><img class=\"media__image media__image--responsive\" alt=\"The increasing number of concussions in football has prompted one school board member in Dover, New Hampshire to propose a ban of the sport.\" data-src-mini=\"http://i2.cdn.turner.com/cnnnext/dam/assets/121015115930-football-kids-concussions-1-small-169.jpg\" data-src-xsmall=\"http://i2.cdn.turner.com/cnnnext/dam/assets/121015115930-football-kids-concussions-1-medium-plus-169.jpg\" data-src-small=\"http://i2.cdn.turner.com/cnnnext/dam/assets/121015115930-football-kids-concussions-1-large-169.jpg\" data-src-medium=\"http://i2.cdn.turner.com/cnnnext/dam/assets/121015115930-football-kids-concussions-1-exlarge-169.jpg\" data-src-large=\"http://i2.cdn.turner.com/cnnnext/dam/assets/121015115930-football-kids-concussions-1-super-169.jpg\" data-src-full16x9=\"http://i2.cdn.turner.com/cnnnext/dam/assets/121015115930-football-kids-concussions-1-full-169.jpg\" data-src-mini1x1=\"http://i2.cdn.turner.com/cnnnext/dam/assets/121015115930-football-kids-concussions-1-small-11.jpg\" data-demand-load=\"not-loaded\" data-eq-pts=\"mini: 0, xsmall: 221, small: 308, medium: 461, large: 781\" src=\"data:image/gif;base64,R0lGODlhEAAJAJEAAAAAAP///////wAAACH5BAEAAAIALAAAAAAQAAkAAAIKlI+py+0Po5yUFQA7\" />\r\n<div class=\"img__preloader\"></div>\r\n\r\n<noscript><img alt=\"The increasing number of concussions in football has prompted one school board member in Dover, New Hampshire to propose a ban of the sport.\" class=\"media__image\" src=\"http://i2.cdn.turner.com/cnnnext/dam/assets/121015115930-football-kids-concussions-1-large-169.jpg\" /></noscript></a></div>\r\n\r\n<div class=\"cd__content\">\r\n<h3 class=\"cd__headline\" data-analytics=\"The%20latest%20from%20CNN%20Health_list-small-horizontal_article_\"><a href=\"/2015/09/18/health/high-school-football-injuries/index.html\"><span class=\"cd__headline-text\">Keeping young players safe on the football field</span></a></h3>\r\n</div>\r\n</div>\r\n</article>\r\n</li>\r\n\r\n<li>\r\n<article class=\"cd cd--card cd--article cd--idx-5 cd--small cd--horizontal cd--has-siblings cd--has-media cd--media__image\" data-vr-contentbox=\"/2015/09/14/health/hand-sanitizer-poisoning/index.html\" data-eq-pts=\"xsmall: 0, small: 300, medium: 460, large: 780, full16x9: 1100\">\r\n<div class=\"cd__wrapper\" data-analytics=\"The%20latest%20from%20CNN%20Health_list-small-horizontal_article_\">\r\n<div class=\"media\"><a href=\"/2015/09/14/health/hand-sanitizer-poisoning/index.html\"><img class=\"media__image media__image--responsive\" alt=\"\" data-src-mini=\"http://i2.cdn.turner.com/cnnnext/dam/assets/150911164931-hand-sanitizer-stock-small-169.jpg\" data-src-xsmall=\"http://i2.cdn.turner.com/cnnnext/dam/assets/150911164931-hand-sanitizer-stock-medium-plus-169.jpg\" data-src-small=\"http://i2.cdn.turner.com/cnnnext/dam/assets/150911164931-hand-sanitizer-stock-large-169.jpg\" data-src-medium=\"http://i2.cdn.turner.com/cnnnext/dam/assets/150911164931-hand-sanitizer-stock-exlarge-169.jpg\" data-src-large=\"http://i2.cdn.turner.com/cnnnext/dam/assets/150911164931-hand-sanitizer-stock-super-169.jpg\" data-src-full16x9=\"http://i2.cdn.turner.com/cnnnext/dam/assets/150911164931-hand-sanitizer-stock-full-169.jpg\" data-src-mini1x1=\"http://i2.cdn.turner.com/cnnnext/dam/assets/150911164931-hand-sanitizer-stock-small-11.jpg\" data-demand-load=\"not-loaded\" data-eq-pts=\"mini: 0, xsmall: 221, small: 308, medium: 461, large: 781\" src=\"data:image/gif;base64,R0lGODlhEAAJAJEAAAAAAP///////wAAACH5BAEAAAIALAAAAAAQAAkAAAIKlI+py+0Po5yUFQA7\" />\r\n<div class=\"img__preloader\"></div>\r\n\r\n<noscript><img alt=\"\" class=\"media__image\" src=\"http://i2.cdn.turner.com/cnnnext/dam/assets/150911164931-hand-sanitizer-stock-large-169.jpg\" /></noscript></a></div>\r\n\r\n<div class=\"cd__content\">\r\n<h3 class=\"cd__headline\" data-analytics=\"The%20latest%20from%20CNN%20Health_list-small-horizontal_article_\"><a href=\"/2015/09/14/health/hand-sanitizer-poisoning/index.html\"><span class=\"cd__headline-text\">More children getting drunk on hand sanitizer</span></a></h3>\r\n</div>\r\n</div>\r\n</article>\r\n</li>\r\n</ul>\r\n</div>\r\n\r\n<div class=\"column\">\r\n<div class=\"ad ad--epic ad--tablet\" data-ad-text=\"show\">\r\n<div data-ad-id=\"freewheel-rail-placeholder\" data-ad-position=\"tablet\" data-ad-refresh=\"default\"></div>\r\n</div>\r\n\r\n<div class=\"ad ad--epic ad--tablet\" data-ad-text=\"show\">\r\n<div data-ad-id=\"ad_rect_atf_01\" data-ad-position=\"tablet\" data-ad-refresh=\"adtop\"></div>\r\n</div>\r\n\r\n<ul class=\"cn cn-list-hierarchical-small-horizontal cn--idx-1 cn-\">\r\n<li>\r\n<article class=\"cd cd--tool cd--tool__outbrain\" data-analytics=\"tool-type_list-hierarchical-small-horizontal_outbrain\" data-vr-contentbox=\"\" data-eq-pts=\"xsmall: 0, small: 300, medium: 460, large: 780\">\r\n<div class=\"OB_HOP_30\">\r\n<div class=\"OUTBRAIN js-m-outbrain m-outbrain\" data-src=\"http://www.cnn.com/2015/09/23/health/saving-lives-worlds-suicide-hot-spots/index.html\" data-widget-id=\"HOP_30\" data-ob-template=\"cnn\" data-widget-type=\"hp\"></div>\r\n</div>\r\n</article>\r\n</li>\r\n</ul>\r\n</div>\r\n\r\n<div class=\"column\">\r\n<ul class=\"cn cn-list-hierarchical-small-horizontal cn--idx-2 cn-\">\r\n<li>\r\n<article class=\"cd cd--tool cd--tool__outbrain\" data-analytics=\"tool-type_list-hierarchical-small-horizontal_outbrain\" data-vr-contentbox=\"\" data-eq-pts=\"xsmall: 0, small: 300, medium: 460, large: 780\">\r\n<div class=\"OB_AR_18\">\r\n<div class=\"OUTBRAIN js-m-outbrain m-outbrain\" data-src=\"http://www.cnn.com/2015/09/23/health/saving-lives-worlds-suicide-hot-spots/index.html\" data-widget-id=\"AR_18\" data-ob-template=\"cnn\"></div>\r\n</div>\r\n</article>\r\n</li>\r\n</ul>\r\n</div>\r\n\r\n<div class=\"column\">\r\n<ul class=\"cn cn-list-hierarchical-small-horizontal cn--idx-3 cn-\">\r\n<li>\r\n<article class=\"cd cd--tool cd--tool__outbrain\" data-analytics=\"tool-type_list-hierarchical-small-horizontal_outbrain\" data-vr-contentbox=\"\" data-eq-pts=\"xsmall: 0, small: 300, medium: 460, large: 780\">\r\n<div class=\"OB_AR_14\">\r\n<div class=\"OUTBRAIN js-m-outbrain m-outbrain\" data-src=\"http://www.cnn.com/2015/09/23/health/saving-lives-worlds-suicide-hot-spots/index.html\" data-widget-id=\"AR_14\" data-ob-template=\"cnn\"></div>\r\n</div>\r\n</article>\r\n</li>\r\n</ul>\r\n</div>\r\n\r\n<div class=\"column\">\r\n<ul class=\"cn cn-list-hierarchical-small-horizontal cn--idx-4 cn-\">\r\n<li>\r\n<article class=\"cd cd--tool cd--tool__outbrain\" data-analytics=\"tool-type_list-hierarchical-small-horizontal_outbrain\" data-vr-contentbox=\"\" data-eq-pts=\"xsmall: 0, small: 300, medium: 460, large: 780\">\r\n<div class=\"OB_AR_19\">\r\n<div class=\"OUTBRAIN js-m-outbrain m-outbrain\" data-src=\"http://www.cnn.com/2015/09/23/health/saving-lives-worlds-suicide-hot-spots/index.html\" data-widget-id=\"AR_19\" data-ob-template=\"cnn\"></div>\r\n</div>\r\n</article>\r\n</li>\r\n</ul>\r\n</div>\r\n</div>\r\n</div>\r\n</section>\r\n\r\n<section class=\"zn zn-topics-and-profile zn-staggered zn--idx-1 zn-has-multiple-containers zn-has-3-containers\" data-eq-pts=\"xsmall: 0, medium: 460, large: 780, full16x9: 1100\" id=\"topics-and-profile\" data-vr-zone=\"zone-2-1\">\r\n<div class=\"zn-top\">\r\n<div class=\"zn-top__background\"></div>\r\n</div>\r\n\r\n<div class=\"l-container zn__background--content-relative\">\r\n<div class=\"zn__containers\" id=\"staggered1\">\r\n<div class=\"column zn-staggered__col\">\r\n<div class=\"ad ad--epic ad--desktop\" data-ad-text=\"show\">\r\n<div data-ad-id=\"ad_rect_btf_01\" data-ad-position=\"desktop\" data-ad-refresh=\"adbody\"></div>\r\n</div>\r\n\r\n<ul class=\"cn cn-list-small-horizontal cn--idx-0 cn-related-stories-topic\">\r\n<li style=\"list-style: none\">\r\n<h2 class=\"cn__title \" data-analytics=\"More%20from%20Health_list-small-horizontal_\">More from Health</h2>\r\n</li>\r\n\r\n<li>\r\n<article class=\"cd cd--card cd--video cd--idx-0 cd--small cd--horizontal cd--has-siblings cd--has-media cd--media__image\" data-vr-contentbox=\"/videos/us/2015/10/02/oregon-shooting-victims-hospital-sot.cnn\" data-eq-pts=\"xsmall: 0, small: 300, medium: 460, large: 780, full16x9: 1100\" data-video-id=\"us/2015/10/02/oregon-shooting-victims-hospital-sot.cnn\">\r\n<div class=\"cd__wrapper\" data-analytics=\"More%20from%20Health_list-small-horizontal_video_video\">\r\n<div class=\"media\"><a href=\"/videos/us/2015/10/02/oregon-shooting-victims-hospital-sot.cnn\"><img class=\"media__image media__image--responsive\" alt=\"\" data-src-mini=\"http://i2.cdn.turner.com/cnnnext/dam/assets/151002142832-oregon-shooting-victim-presser-small-169.jpg\" data-src-xsmall=\"http://i2.cdn.turner.com/cnnnext/dam/assets/151002142832-oregon-shooting-victim-presser-medium-plus-169.jpg\" data-src-small=\"http://i2.cdn.turner.com/cnnnext/dam/assets/151002142832-oregon-shooting-victim-presser-large-169.jpg\" data-src-medium=\"http://i2.cdn.turner.com/cnnnext/dam/assets/151002142832-oregon-shooting-victim-presser-exlarge-169.jpg\" data-src-large=\"http://i2.cdn.turner.com/cnnnext/dam/assets/151002142832-oregon-shooting-victim-presser-super-169.jpg\" data-src-full16x9=\"http://i2.cdn.turner.com/cnnnext/dam/assets/151002142832-oregon-shooting-victim-presser-full-169.jpg\" data-src-mini1x1=\"http://i2.cdn.turner.com/cnnnext/dam/assets/151002142832-oregon-shooting-victim-presser-small-11.jpg\" data-demand-load=\"not-loaded\" data-eq-pts=\"mini: 0, xsmall: 221, small: 308, medium: 461, large: 781\" src=\"data:image/gif;base64,R0lGODlhEAAJAJEAAAAAAP///////wAAACH5BAEAAAIALAAAAAAQAAkAAAIKlI+py+0Po5yUFQA7\" />\r\n<div class=\"img__preloader\"></div>\r\n\r\n<noscript><img alt=\"\" class=\"media__image\" src=\"http://i2.cdn.turner.com/cnnnext/dam/assets/151002142832-oregon-shooting-victim-presser-large-169.jpg\" /></noscript></a></div>\r\n\r\n<div class=\"cd__content\">\r\n<h3 class=\"cd__headline\" data-analytics=\"More%20from%20Health_list-small-horizontal_video_video\"><a href=\"/videos/us/2015/10/02/oregon-shooting-victims-hospital-sot.cnn\"><span class=\"cd__headline-text\">Doctor: Two shooting victims 'intubated and sedated'</span></a></h3>\r\n</div>\r\n</div>\r\n</article>\r\n</li>\r\n\r\n<li>\r\n<article class=\"cd cd--card cd--story cd--idx-1 cd--small cd--horizontal cd--has-siblings cd--has-media cd--media__image\" data-vr-contentbox=\"/2015/10/02/health/acronyms-teens-social-media-being13/index.html\" data-eq-pts=\"xsmall: 0, small: 300, medium: 460, large: 780, full16x9: 1100\">\r\n<div class=\"cd__wrapper\" data-analytics=\"More%20from%20Health_list-small-horizontal_story_\">\r\n<div class=\"media\"><a href=\"/2015/10/02/health/acronyms-teens-social-media-being13/index.html\"><img class=\"media__image media__image--responsive\" alt=\"anderson cooper reporters notebook being 13_00005728.jpg\" data-src-mini=\"http://i2.cdn.turner.com/cnnnext/dam/assets/150908183254-anderson-cooper-reporters-notebook-being-13-00005728-small-169.jpg\" data-src-xsmall=\"http://i2.cdn.turner.com/cnnnext/dam/assets/150908183254-anderson-cooper-reporters-notebook-being-13-00005728-medium-plus-169.jpg\" data-src-small=\"http://i2.cdn.turner.com/cnnnext/dam/assets/150908183254-anderson-cooper-reporters-notebook-being-13-00005728-large-169.jpg\" data-src-medium=\"http://i2.cdn.turner.com/cnnnext/dam/assets/150908183254-anderson-cooper-reporters-notebook-being-13-00005728-exlarge-169.jpg\" data-src-large=\"http://i2.cdn.turner.com/cnnnext/dam/assets/150908183254-anderson-cooper-reporters-notebook-being-13-00005728-super-169.jpg\" data-src-full16x9=\"http://i2.cdn.turner.com/cnnnext/dam/assets/150908183254-anderson-cooper-reporters-notebook-being-13-00005728-full-169.jpg\" data-src-mini1x1=\"http://i2.cdn.turner.com/cnnnext/dam/assets/150908183254-anderson-cooper-reporters-notebook-being-13-00005728-small-11.jpg\" data-demand-load=\"not-loaded\" data-eq-pts=\"mini: 0, xsmall: 221, small: 308, medium: 461, large: 781\" src=\"data:image/gif;base64,R0lGODlhEAAJAJEAAAAAAP///////wAAACH5BAEAAAIALAAAAAAQAAkAAAIKlI+py+0Po5yUFQA7\" />\r\n<div class=\"img__preloader\"></div>\r\n\r\n<noscript><img alt=\"anderson cooper reporters notebook being 13_00005728.jpg\" class=\"media__image\" src=\"http://i2.cdn.turner.com/cnnnext/dam/assets/150908183254-anderson-cooper-reporters-notebook-being-13-00005728-large-169.jpg\" /></noscript></a></div>\r\n\r\n<div class=\"cd__content\">\r\n<h3 class=\"cd__headline\" data-analytics=\"More%20from%20Health_list-small-horizontal_story_\"><a href=\"/2015/10/02/health/acronyms-teens-social-media-being13/index.html\"><span class=\"cd__headline-text\">The acronyms teens really use on social media</span></a></h3>\r\n</div>\r\n</div>\r\n</article>\r\n</li>\r\n\r\n<li>\r\n<article class=\"cd cd--card cd--story cd--idx-2 cd--small cd--horizontal cd--has-siblings cd--has-media cd--media__image\" data-vr-contentbox=\"/2015/09/28/health/workplace-wellness-privacy-risk-exclusive/index.html\" data-eq-pts=\"xsmall: 0, small: 300, medium: 460, large: 780, full16x9: 1100\">\r\n<div class=\"cd__wrapper\" data-analytics=\"More%20from%20Health_list-small-horizontal_story_\">\r\n<div class=\"media\"><a href=\"/2015/09/28/health/workplace-wellness-privacy-risk-exclusive/index.html\"><img class=\"media__image media__image--responsive\" alt=\"\" data-src-mini=\"http://i2.cdn.turner.com/cnnnext/dam/assets/150925153753-work-fitness-program-small-169.jpg\" data-src-xsmall=\"http://i2.cdn.turner.com/cnnnext/dam/assets/150925153753-work-fitness-program-medium-plus-169.jpg\" data-src-small=\"http://i2.cdn.turner.com/cnnnext/dam/assets/150925153753-work-fitness-program-large-169.jpg\" data-src-medium=\"http://i2.cdn.turner.com/cnnnext/dam/assets/150925153753-work-fitness-program-exlarge-169.jpg\" data-src-large=\"http://i2.cdn.turner.com/cnnnext/dam/assets/150925153753-work-fitness-program-super-169.jpg\" data-src-full16x9=\"http://i2.cdn.turner.com/cnnnext/dam/assets/150925153753-work-fitness-program-full-169.jpg\" data-src-mini1x1=\"http://i2.cdn.turner.com/cnnnext/dam/assets/150925153753-work-fitness-program-small-11.jpg\" data-demand-load=\"not-loaded\" data-eq-pts=\"mini: 0, xsmall: 221, small: 308, medium: 461, large: 781\" src=\"data:image/gif;base64,R0lGODlhEAAJAJEAAAAAAP///////wAAACH5BAEAAAIALAAAAAAQAAkAAAIKlI+py+0Po5yUFQA7\" />\r\n<div class=\"img__preloader\"></div>\r\n\r\n<noscript><img alt=\"\" class=\"media__image\" src=\"http://i2.cdn.turner.com/cnnnext/dam/assets/150925153753-work-fitness-program-large-169.jpg\" /></noscript></a></div>\r\n\r\n<div class=\"cd__content\">\r\n<h3 class=\"cd__headline\" data-analytics=\"More%20from%20Health_list-small-horizontal_story_\"><a href=\"/2015/09/28/health/workplace-wellness-privacy-risk-exclusive/index.html\"><span class=\"cd__headline-text\">Workplace wellness programs put employee privacy at risk</span></a></h3>\r\n</div>\r\n</div>\r\n</article>\r\n</li>\r\n</ul>\r\n\r\n<div class=\"ad ad--epic ad--tablet\" data-ad-text=\"show\">\r\n<div data-ad-id=\"ad_rect_btf_01\" data-ad-position=\"tablet\" data-ad-refresh=\"adbody\"></div>\r\n</div>\r\n\r\n<ul class=\"cn cn-list-small-horizontal cn--idx-2 cn-lukxas cn--expandable\">\r\n<li>\r\n<article class=\"cd cd--tool cd--tool__feed\" data-analytics=\"tool-type_list-small-horizontal_feed\" data-vr-contentbox=\"\" data-eq-pts=\"xsmall: 0, small: 300, medium: 460, large: 780\">\r\n<div class=\"cd-feed__wrapper\"><a class=\"cn__title--link\" href=\"http://inhealth.cnn.com\" target=\"_new\">\r\n<h2 class=\"cn__title\">Healthgrades</h2>\r\n</a>\r\n<article class=\"cd cd--card cd--hyperlink cd--lang-en cd--idx-0 cd--extra-small\" data-eq-pts=\"xsmall: 0, medium: 460, large: 780\">\r\n<div class=\"cd__wrapper\" data-analytics=\"Healthgrades_list-small-horizontal__\">\r\n<div class=\"cd-feed__content\">\r\n<h3 class=\"cd__headline\"><a data-vr-track=\"data-vr-track\" href=\"http://www.healthgrades.com/right-care/psoriasis/a-look-at-psoriasis-severity?cid=t1_rss2&amp;sr=C53310a10\"><span class=\"cd__headline-text\">How severe is your psoriasis?</span></a></h3>\r\n</div>\r\n</div>\r\n</article>\r\n\r\n<article class=\"cd cd--card cd--hyperlink cd--lang-en cd--idx-1 cd--extra-small\" data-eq-pts=\"xsmall: 0, medium: 460, large: 780\">\r\n<div class=\"cd__wrapper\" data-analytics=\"Healthgrades_list-small-horizontal__\">\r\n<div class=\"cd-feed__content\">\r\n<h3 class=\"cd__headline\"><a data-vr-track=\"data-vr-track\" href=\"http://www.healthgrades.com/provider-search-directory/search?q=Dermatology&amp;prof.type=provider&amp;search.type=PracticingSpecialty&amp;loc=locIsSolrCity%3Dfalse%3Fcid%3Dt1_rss2&amp;sr=C53310a10\"><span class=\"cd__headline-text\">Find a great dermatologist near you</span></a></h3>\r\n</div>\r\n</div>\r\n</article>\r\n\r\n<article class=\"cd cd--card cd--hyperlink cd--lang-en cd--idx-2 cd--extra-small\" data-eq-pts=\"xsmall: 0, medium: 460, large: 780\">\r\n<div class=\"cd__wrapper\" data-analytics=\"Healthgrades_list-small-horizontal__\">\r\n<div class=\"cd-feed__content\">\r\n<h3 class=\"cd__headline\"><a data-vr-track=\"data-vr-track\" href=\"http://www.healthgrades.com/right-care/birth-control/12-things-your-ob-gyn-wants-you-to-know?cid=t1_rss2&amp;sr=C53310a10\"><span class=\"cd__headline-text\">12 things your OB/GYN wants you to know</span></a></h3>\r\n</div>\r\n</div>\r\n</article>\r\n\r\n<article class=\"cd cd--card cd--hyperlink cd--lang-en cd--idx-3 cd--extra-small\" data-eq-pts=\"xsmall: 0, medium: 460, large: 780\">\r\n<div class=\"cd__wrapper\" data-analytics=\"Healthgrades_list-small-horizontal__\">\r\n<div class=\"cd-feed__content\">\r\n<h3 class=\"cd__headline\"><a data-vr-track=\"data-vr-track\" href=\"http://www.healthgrades.com/conditions/how-to-talk-with-your-doctor-about-sex?cid=t1_rss2&amp;sr=C53310a10\"><span class=\"cd__headline-text\">How to talk to your doctor about sex</span></a></h3>\r\n</div>\r\n</div>\r\n</article>\r\n\r\n<article class=\"cd cd--card cd--hyperlink cd--lang-en cd--idx-4 cd--extra-small\" data-eq-pts=\"xsmall: 0, medium: 460, large: 780\">\r\n<div class=\"cd__wrapper\" data-analytics=\"Healthgrades_list-small-horizontal__\">\r\n<div class=\"cd-feed__content\">\r\n<h3 class=\"cd__headline\"><a data-vr-track=\"data-vr-track\" href=\"http://www.healthgrades.com/conditions/8-things-to-know-about-ibs?cid=t1_rss2&amp;sr=C53310a10\"><span class=\"cd__headline-text\">8 things to know about IBS</span></a></h3>\r\n</div>\r\n</div>\r\n</article>\r\n</div>\r\n</article>\r\n</li>\r\n</ul>\r\n</div>\r\n\r\n<div class=\"column zn-staggered__col\"></div>\r\n\r\n<div class=\"column zn-staggered__col\"></div>\r\n</div>\r\n</div>\r\n</section>\r\n\r\n<section class=\"zn zn- zn-body zn--idx-2 zn-has-one-container\" data-eq-pts=\"xsmall: 0, medium: 460, large: 780, full16x9: 1100\" id=\"\" data-vr-zone=\"zone-2-2\" data-containers=\"1\">\r\n<div class=\"ad ad--epic ad--desktop\" data-ad-text=\"show\">\r\n<div id=\"ad_rect_btf_04\" class=\"ad-ad_rect_btf_04 ad-refresh-adbody\"></div>\r\n</div>\r\n\r\n<div class=\"l-container\"></div>\r\n</section>\r\n</div>\r\n\r\n<div class=\"pg-comments pg-rail-tall__comments\">\r\n<div id='ym_764345183319563885' class='ym'></div>\r\n</div>\r\n</div>\r\n</div>\r\n\r\n<div class=\"pg-below-rail\"></div>\r\n</article>\r\n</div>\r\n\r\n<div class=\"cmcs-subscription-wrapper l-footer\">\r\n<div class=\"js-cmcs-footer-card l-footer__content\"></div>\r\n</div>\r\n\r\n<footer class=\"l-footer\">\r\n<div class=\"l-footer__tools\">\r\n<div class=\"l-footer__tools--weather\">\r\n<div class=\"l-footer__weather weather__footer\" id=\"js-weather__footer\"></div>\r\n</div>\r\n\r\n<div class=\"l-footer__search search__footer\">\r\n<form method=\"get\" action=\"/search/\" name=\"footerSearch\" class=\"search__footer--form\"><input type=\"text\" placeholder=\"Search CNN\" id=\"searchInputFooter\" name=\"text\" class=\"search-input__text\" /></form>\r\n</div>\r\n</div>\r\n\r\n<div class=\"l-footer__content\">\r\n<div class=\"m-footer-nav edition-domestic\">\r\n<div class=\"m-footer__bucket_group\">\r\n<ol class=\"m-footer__bucket m-footer__bucket__news\">\r\n<li class=\"m-footer__title\"><a class=\"m-footer__title__link\" href=\"/\" data-analytics=\"footer_news\">News</a>\r\n<ol class=\"m-footer__subtitles m-footer__subtitles--news\">\r\n<li class=\"m-footer__list-item\"><a class=\"m-footer__link\" data-analytics=\"footer_news_us\" href=\"/us\">U.S.</a></li>\r\n\r\n<li class=\"m-footer__list-item\"><a class=\"m-footer__link\" data-analytics=\"footer_news_world\" href=\"/world\">World</a></li>\r\n\r\n<li class=\"m-footer__list-item\"><a class=\"m-footer__link\" data-analytics=\"footer_news_politics\" href=\"/politics\">Politics</a></li>\r\n\r\n<li class=\"m-footer__list-item\"><a class=\"m-footer__link\" data-analytics=\"footer_news_tech\" href=\"/tech\">Tech</a></li>\r\n\r\n<li class=\"m-footer__list-item\"><a class=\"m-footer__link\" data-analytics=\"footer_news_health\" href=\"/health\">Health</a></li>\r\n\r\n<li class=\"m-footer__list-item\"><a class=\"m-footer__link\" data-analytics=\"footer_news_entertainment\" href=\"/entertainment\">Entertainment</a></li>\r\n\r\n<li class=\"m-footer__list-item\"><a class=\"m-footer__link\" data-analytics=\"footer_news_living\" href=\"/living\">Living</a></li>\r\n\r\n<li class=\"m-footer__list-item\"><a class=\"m-footer__link\" data-analytics=\"footer_news_travel\" href=\"/travel\">Travel</a></li>\r\n\r\n<li class=\"m-footer__list-item\"><a class=\"m-footer__link\" data-analytics=\"footer_news_money\" href=\"//money.cnn.com\">Money</a></li>\r\n\r\n<li class=\"m-footer__list-item\"><a class=\"m-footer__link\" data-analytics=\"footer_news_sports\" href=\"//bleacherreport.com\">Sports</a></li>\r\n</ol>\r\n</li>\r\n</ol>\r\n\r\n<ol class=\"m-footer__bucket m-footer__bucket__video\">\r\n<li class=\"m-footer__title\"><a class=\"m-footer__title__link\" href=\"/videos\" data-analytics=\"footer_video\">Video</a>\r\n<ol class=\"m-footer__subtitles m-footer__subtitles--video\">\r\n<li class=\"m-footer__list-item\"><a class=\"m-footer__link\" data-analytics=\"footer_video_cnngo\" href=\"//cnn.it/go\">CNNgo</a></li>\r\n\r\n<li class=\"m-footer__list-item\"><a class=\"m-footer__link\" data-analytics=\"footer_video_latest-news\" href=\"/specials/latest-news-videos\">Latest News</a></li>\r\n\r\n<li class=\"m-footer__list-item\"><a class=\"m-footer__link\" data-analytics=\"footer_video_must-watch-videos\" href=\"/specials/video-landing/gotta-watch-video-collection\">Must Watch Videos</a></li>\r\n\r\n<li class=\"m-footer__list-item\"><a class=\"m-footer__link\" data-analytics=\"footer_video_digital-studios\" href=\"/specials/digital-studios\">Digital Studios</a></li>\r\n</ol>\r\n</li>\r\n</ol>\r\n\r\n<ol class=\"m-footer__bucket m-footer__bucket__tv\">\r\n<li class=\"m-footer__title\"><a class=\"m-footer__title__link\" href=\"/tv\" data-analytics=\"footer_tv\">TV</a>\r\n<ol class=\"m-footer__subtitles m-footer__subtitles--tv\">\r\n<li class=\"m-footer__list-item\"><a class=\"m-footer__link\" data-analytics=\"footer_tv_cnngo\" href=\"//cnn.it/go\">CNNgo</a></li>\r\n\r\n<li class=\"m-footer__list-item\"><a class=\"m-footer__link\" data-analytics=\"footer_tv_schedule\" href=\"/tv/schedule/cnn\">Schedule</a></li>\r\n\r\n<li class=\"m-footer__list-item\"><a class=\"m-footer__link\" data-analytics=\"footer_tv_cnn-films\" href=\"/shows/cnn-films\">CNN Films</a></li>\r\n\r\n<li class=\"m-footer__list-item\"><a class=\"m-footer__link\" data-analytics=\"footer_tv_shows-a-z\" href=\"/specials/tv/all-shows\">Shows A-Z</a></li>\r\n\r\n<li class=\"m-footer__list-item\"><a class=\"m-footer__link\" data-analytics=\"footer_tv_faces-of-cnn-worldwide\" href=\"/specials/tv/anchors-and-reporters\">Faces of CNN Worldwide</a></li>\r\n</ol>\r\n</li>\r\n</ol>\r\n\r\n<ol class=\"m-footer__bucket m-footer__bucket__opinions\">\r\n<li class=\"m-footer__title\"><a class=\"m-footer__title__link\" href=\"/opinions\" data-analytics=\"footer_opinions\">Opinions</a>\r\n<ol class=\"m-footer__subtitles m-footer__subtitles--opinions\">\r\n<li class=\"m-footer__list-item\"><a class=\"m-footer__link\" data-analytics=\"footer_opinions_political-op-eds\" href=\"/specials/opinion/opinion-politics\">Political Op-Eds</a></li>\r\n\r\n<li class=\"m-footer__list-item\"><a class=\"m-footer__link\" data-analytics=\"footer_opinions_social-commentary\" href=\"/specials/opinion/opinion-social-issues\">Social Commentary</a></li>\r\n\r\n<li class=\"m-footer__list-item\"><a class=\"m-footer__link\" data-analytics=\"footer_opinions_ireport\" href=\"//ireport.cnn.com\">iReport</a></li>\r\n</ol>\r\n</li>\r\n</ol>\r\n\r\n<ol class=\"m-footer__bucket m-footer__bucket__more\">\r\n<li class=\"m-footer__title\"><a class=\"m-footer__title__link\" href=\"/more\" data-analytics=\"footer_more\">More…</a>\r\n<ol class=\"m-footer__subtitles m-footer__subtitles--more\">\r\n<li class=\"m-footer__list-item\"><a class=\"m-footer__link\" data-analytics=\"footer_more_photos\" href=\"/specials/photos\">Photos</a></li>\r\n\r\n<li class=\"m-footer__list-item\"><a class=\"m-footer__link\" data-analytics=\"footer_more_longform\" href=\"/specials/cnn-longform\">Longform</a></li>\r\n\r\n<li class=\"m-footer__list-item\"><a class=\"m-footer__link\" data-analytics=\"footer_more_investigations\" href=\"/specials/cnn-investigations\">Investigations</a></li>\r\n\r\n<li class=\"m-footer__list-item\"><a class=\"m-footer__link\" data-analytics=\"footer_more_cnn-profiles-a-z\" href=\"/specials/profiles/\">CNN profiles A-Z</a></li>\r\n\r\n<li class=\"m-footer__list-item\"><a class=\"m-footer__link\" data-analytics=\"footer_more_cnn-leadership\" href=\"/specials/more/cnn-leadership\">CNN Leadership</a></li>\r\n</ol>\r\n</li>\r\n</ol>\r\n</div>\r\n\r\n<div class=\"m-copyright-outercontainer\">\r\n<div class=\"edition-picker\"><a class=\"logo\" href=\"/\" data-analytics=\"edition-picker-logo\"></a>\r\n<div class=\"drop-down\">\r\n<div class=\"current\">U.S. Edition</div>\r\n\r\n<ul class=\"list js-edition-picker__list\" data-location=\"footer\" data-analytics=\"edition-picker\">\r\n<li class=\"item item--option selected\" data-value=\"http://us.cnn.com\"><input id=\"edition-picker--edtion-footer\" type=\"radio\" class=\"js-edition-preferences__choice\" name=\"edition-pref-footer\" value=\"www\" /><label for=\"edition-picker--edtion-footer\">U.S.</label></li>\r\n\r\n<li class=\"item item--option \" data-value=\"http://edition.cnn.com\"><input id=\"edition-picker--www-footer\" type=\"radio\" class=\"js-edition-preferences__choice\" name=\"edition-pref-footer\" value=\"edition\" /><label for=\"edition-picker--www-footer\">International</label></li>\r\n\r\n<li class=\"item\" data-value=\"http://arabic.cnn.com\">Arabic</li>\r\n\r\n<li class=\"item\" data-value=\"http://cnnespanol.cnn.com/\">Español</li>\r\n\r\n<li class=\"item item--select\">Set edition preference</li>\r\n\r\n<li class=\"item item--confirm js-edition-preferences__confirm\">Confirm</li>\r\n</ul>\r\n</div>\r\n</div>\r\n\r\n<div class=\"m-copyright-innercontainer\">\r\n<div class=\"m-copyright\"><span class=\"copyright\">© 2015 Cable News Network. <a class=\"m-copyright__links\" data-analytics=\"footer_turner-broadcasting-system-inc\" href=\"http://www.turner.com\" title=\"Turner Broadcasting System, Inc.\">Turner Broadcasting System, Inc.</a> All Rights Reserved.</span></div>\r\n\r\n<div class=\"m-legal\">\r\n<ul class=\"m-legal__list\">\r\n<li class=\"m-legal__list__item\"><a class=\"m-legal__links\" data-analytics=\"footer_terms-of-use\" href=\"/terms\">Terms of Use</a></li>\r\n\r\n<li class=\"m-legal__list__item\"><a class=\"m-legal__links\" data-analytics=\"footer_privacy-policy\" href=\"/privacy\">Privacy Policy</a></li>\r\n\r\n<li class=\"m-legal__list__item\"><a class=\"m-legal__links\" data-analytics=\"footer_adchoices\" href=\"#\">AdChoices</a></li>\r\n\r\n<li class=\"m-legal__list__item\"><a class=\"m-legal__links\" data-analytics=\"footer_advertise-with-us\" href=\"/services/advertise/main.html\">Advertise with us</a></li>\r\n\r\n<li class=\"m-legal__list__item\"><a class=\"m-legal__links\" data-analytics=\"footer_about-us\" href=\"/about\">About us</a></li>\r\n\r\n<li class=\"m-legal__list__item\"><a class=\"m-legal__links\" data-analytics=\"footer_work-for-us\" href=\"http://www.turner.com/careers\">Work for us</a></li>\r\n\r\n<li class=\"m-legal__list__item\"><a class=\"m-legal__links\" data-analytics=\"footer_help\" href=\"/help\">Help</a></li>\r\n\r\n<li class=\"m-legal__list__item\"><a class=\"m-legal__links\" data-analytics=\"footer_transcripts\" href=\"/transcripts\">Transcripts</a></li>\r\n\r\n<li class=\"m-legal__list__item\"><a class=\"m-legal__links\" data-analytics=\"footer_license-footage\" href=\"/collection\">License Footage</a></li>\r\n\r\n<li class=\"m-legal__list__item last-child\"><a class=\"m-legal__links\" data-analytics=\"footer_cnn-newsource\" href=\"http://cnnnewsource.com\">CNN Newsource</a></li>\r\n</ul>\r\n</div>\r\n</div>\r\n</div>\r\n</div>\r\n</div>\r\n</footer>\r\n\r\n<div class=\"ad ad--epic ad--all-skin\">\r\n<div id=\"ad_oop_skin_01\" class=\"ad-ad_oop_skin_01 ad-refresh-adbanner\"></div>\r\n</div>\r\n</body>\r\n</html>\r\n\r\n"}}